Workbook

Sheet Piutang Pengadaan
A5: AEROSPACE
A6: KARTU ANGSURAN PENGADAAN KOPERASI KARYAWAN
A7: TAHUN 2020
A8: No.Kontrak | B8: NAMA KARYAWAN | C8: Harga Beli | D8: Keuntungan | E8: ANGSURAN | AC8: SALDO
E9: JAN | G9: FEB | I9: MAR | K9: APR | M9: MEI | O9: JUN | Q9: JUL | S9: AGT | U9: SEP | W9: OKT | Y9: NOV | AA9: DES
E10: Pokok | F10: Keuntungan | G10: Pokok | H10: Keuntungan | I10: Pokok | J10: Keuntungan | K10: Pokok | L10: Keuntungan | M10: Pokok | N10: Keuntungan | O10: Pokok | P10: Keuntungan | Q10: Pokok | R10: Keuntungan | S10: Pokok | T10: Keuntungan | U10: Pokok | V10: Keuntungan | W10: Pokok | X10: Keuntungan | Y10: Pokok | Z10: Keuntungan | AA10: Pokok | AB10: Keuntungan | AC10: Pokok | AD10: Keuntungan
B11: Syswahyudi | C11: 2600000 | D11: 388000 | U11: 433333.33 | V11: 64666.667 | W11: 433333.33 | X11: 64666.667 | Y11: 433333.33 | Z11: 64666.667 | AA11: 433333.33 | AB11: 64666.667 | AC11: =+C11-E11-G11-I11-K11-M11-O11-Q11-S11-U11-W11-Y11-AA11 -> 866666.67 | AD11: =+D11-F11-H11-J11-L11-N11-P11-R11-T11-V11-X11-Z11-AB11 -> 129333.33
B12: Adi Ramdani | C12: 1900000 | D12: 290000 | W12: 316666.67 | X12: 48333.333 | Y12: =1266666.66666667+316667 -> 1583333.7 | Z12: =193333.333333333+48333 -> 241666.33 | AC12: =+C12-E12-G12-I12-K12-M12-O12-Q12-S12-U12-W12-Y12-AA12 -> -0.33333334 | AD12: =+D12-F12-H12-J12-L12-N12-P12-R12-T12-V12-X12-Z12-AB12 -> 0.33333333
B13: Ahmad Suwarna | C13: 400000 | D13: 38000 | U13: 400000 | V13: 38000 | AC13: =+C13-E13-G13-I13-K13-M13-O13-Q13-S13-U13-W13-Y13-AA13 -> 0 | AD13: =+D13-F13-H13-J13-L13-N13-P13-R13-T13-V13-X13-Z13-AB13 -> 0
AC14: =+C14-E14-G14-I14-K14-M14-O14-Q14-S14-U14-W14-Y14-AA14 -> 0 | AD14: =+D14-F14-H14-J14-L14-N14-P14-R14-T14-V14-X14-Z14-AB14 -> 0
AC15: =+C15-E15-G15-I15-K15-M15-O15-Q15-S15-U15-W15-Y15-AA15 -> 0 | AD15: =+D15-F15-H15-J15-L15-N15-P15-R15-T15-V15-X15-Z15-AB15 -> 0
D16: =+C16*0.1 -> 0 | AC16: =+C16-E16-G16-I16-K16-M16-O16-Q16-S16-U16-W16-Y16-AA16 -> 0 | AD16: =+D16-F16-H16-J16-L16-N16-P16-R16-T16-V16-X16-Z16-AB16 -> 0
D17: =+C17*0.1 -> 0 | AC17: =+C17-E17-G17-I17-K17-M17-O17-Q17-S17-U17-W17-Y17-AA17 -> 0 | AD17: =+D17-F17-H17-J17-L17-N17-P17-R17-T17-V17-X17-Z17-AB17 -> 0
A18: TOTAL | C18: =SUM(C11:C17) -> 4900000 | D18: =SUM(D11:D17) -> 716000 | E18: =SUM(E11:E17) -> 0 | F18: =SUM(F11:F17) -> 0 | G18: =SUM(G11:G17) -> 0 | H18: =SUM(H11:H17) -> 0 | I18: =SUM(I11:I17) -> 0 | J18: =SUM(J11:J17) -> 0 | ... AD18: =SUM(AD11:AD17) -> 129333.67
AC19: =+E18+G18+I18+K18+M18+O18+Q18+S18+U18+W18+Y18+AA18 -> 4033333.7 | AD19: =+F18+H18+J18+L18+N18+P18+R18+T18+V18+X18+Z18+AB18 -> 586666.33
C20: =+C18/1.1 -> 4454545.5 | AA20: Saldo Kas | AB20: 14395000
AA21: Pitang | AB21: =AC18 -> 866666.33
A22: AEROSPACE
A23: KARTU ANGSURAN PENGADAAN KOPERASI KARYAWAN
A24: TAHUN 2021
A25: No.Kontrak | B25: NAMA KARYAWAN | C25: Harga Beli | D25: Keuntungan | E25: ANGSURAN | AC25: SALDO
E26: JAN | G26: FEB | I26: MAR | K26: APR | M26: MEI | O26: JUN | Q26: JUL | S26: AGT | U26: SEP | W26: OKT | Y26: NOV | AA26: DES
E27: Pokok | F27: Bunga | G27: Pokok | H27: Bunga | I27: Pokok | J27: Bunga | K27: Pokok | L27: Bunga | M27: Pokok | N27: Bunga | O27: Pokok | P27: Bunga | Q27: Pokok | R27: Bunga | S27: Pokok | T27: Bunga | U27: Pokok | V27: Bunga | W27: Pokok | X27: Bunga | Y27: Pokok | Z27: Bunga | AA27: Pokok | AB27: Bunga | AC27: Pokok | AD27: Bunga
A28: 34000118 | B28: Syswahyudi | C28: =AC11 -> 866666.67 | D28: =AD11 -> 129333.33 | E28: 433333.33 | F28: 64666.667 | G28: 433333.33 | H28: 64666.667 | AC28: =+C28-E28-G28-I28-K28-M28-O28-Q28-S28-U28-W28-Y28-AA28 -> 1.1641532e-10 | AD28: =+D28-F28-H28-J28-L28-N28-P28-R28-T28-V28-X28-Z28-AB28 -> 1.4551915e-11 | AE28: =F28+H28+J28+L28+N28+P28+R28+T28+V28+X28+Z28+AB28 -> 129333.33
A29: 34000229 | B29: Erik Fujiwa | C29: 1999999 | D29: 281000 | I29: 166667 | J29: 23333 | K29: 166667 | L29: 23333 | M29: 166667 | N29: 23333 | O29: 166667 | P29: 23333 | Q29: 166667 | R29: 23333 | S29: 166667 | T29: 23333 | U29: 166667 | V29: 23333 | W29: 166667 | X29: 23333 | Y29: 166667 | Z29: 23333 | AA29: 166667 | AB29: 23333 | AC29: =+C29-E29-G29-I29-K29-M29-O29-Q29-S29-U29-W29-Y29-AA29 -> 333329 | AD29: =+D29-F29-H29-J29-L29-N29-P29-R29-T29-V29-X29-Z29-AB29 -> 47670 | AE29: =F29+H29+J29+L29+N29+P29+R29+T29+V29+X29+Z29+AB29 -> 233330
A30: 34000379 | B30: Januar Muharna | C30: 5000000 | D30: 670000 | I30: 416666.67 | J30: 55833.333 | K30: 416666.67 | L30: 55833.333 | M30: 416666.67 | N30: 55833.333 | O30: 416666.67 | P30: 55833.333 | Q30: 416666.67 | R30: 55833.333 | S30: 416666.67 | T30: 55833.333 | U30: 416666.67 | V30: 55833.333 | W30: 416666.67 | X30: 55833.333 | Y30: 416666.67 | Z30: 55833.333 | AA30: 416666.67 | AB30: 55833.333 | AC30: =+C30-E30-G30-I30-K30-M30-O30-Q30-S30-U30-W30-Y30-AA30 -> 833333.33 | AD30: =+D30-F30-H30-J30-L30-N30-P30-R30-T30-V30-X30-Z30-AB30 -> 111666.67 | AE30: =F30+H30+J30+L30+N30+P30+R30+T30+V30+X30+Z30+AB30 -> 558333.33
A31: 34000118 | B31: Syswahyudi | C31: 2500000 | D31: 380000 | I31: 416666.67 | J31: 63333.333 | K31: 416666.67 | L31: 63333.333 | M31: 416666.67 | N31: 63333.333 | O31: 416666.67 | P31: 63333.333 | Q31: 416666.67 | R31: 63333.333 | S31: 416666.67 | T31: 63333.333 | AC31: =+C31-E31-G31-I31-K31-M31-O31-Q31-S31-U31-W31-Y31-AA31 -> -3.4924597e-10 | AD31: =+D31-F31-H31-J31-L31-N31-P31-R31-T31-V31-X31-Z31-AB31 -> -1.4551915e-11 | AE31: =F31+H31+J31+L31+N31+P31+R31+T31+V31+X31+Z31+AB31 -> 380000
A32: 34000351 | B32: Ari Rosandi | C32: 2298000 | D32: 352000 | I32: 229800 | J32: 35200 | K32: 229800 | L32: 35200 | M32: 229800 | N32: 35200 | O32: 229800 | P32: 35200 | Q32: 229800 | R32: 35200 | S32: 229800 | T32: 35200 | U32: 229800 | V32: 35200 | W32: 229800 | X32: 35200 | Y32: 229800 | Z32: 35200 | AA32: 229800 | AB32: 35200 | AC32: =+C32-E32-G32-I32-K32-M32-O32-Q32-S32-U32-W32-Y32-AA32 -> 0 | AD32: =+D32-F32-H32-J32-L32-N32-P32-R32-T32-V32-X32-Z32-AB32 -> 0 | AE32: =F32+H32+J32+L32+N32+P32+R32+T32+V32+X32+Z32+AB32 -> 352000
A33: 34000203 | B33: Bonny Aries | C33: 3000000 | D33: 396000 | K33: 250000 | L33: 33000 | M33: 250000 | N33: 33000 | O33: 250000 | P33: 33000 | Q33: 250000 | R33: 33000 | S33: 250000 | T33: 33000 | U33: 250000 | V33: 33000 | W33: 250000 | X33: 33000 | Y33: 250000 | Z33: 33000 | AA33: 250000 | AB33: 33000 | AC33: =+C33-E33-G33-I33-K33-M33-O33-Q33-S33-U33-W33-Y33-AA33 -> 750000 | AD33: =+D33-F33-H33-J33-L33-N33-P33-R33-T33-V33-X33-Z33-AB33 -> 99000 | AE33: =F33+H33+J33+L33+N33+P33+R33+T33+V33+X33+Z33+AB33 -> 297000
A34: 34000514 | B34: Adifia Pramana | C34: 3499000 | D34: 401000 | K34: 291583.33 | L34: 33416.667 | M34: 291583.33 | N34: 33416.667 | O34: 291583.33 | P34: 33416.667 | Q34: 291583.33 | R34: 33416.667 | S34: 291583.33 | T34: 33416.667 | U34: 291583.33 | V34: 33416.667 | W34: 291583.33 | X34: 33416.667 | Y34: 291583.33 | Z34: 33416.667 | AA34: 291583.33 | AB34: 33416.667 | AC34: =+C34-E34-G34-I34-K34-M34-O34-Q34-S34-U34-W34-Y34-AA34 -> 874750 | AD34: =+D34-F34-H34-J34-L34-N34-P34-R34-T34-V34-X34-Z34-AB34 -> 100250 | AE34: =F34+H34+J34+L34+N34+P34+R34+T34+V34+X34+Z34+AB34 -> 300750
A35: 34000354 | B35: Ahmad Suwarna | C35: 3630000 | D35: 390000 | K35: 302500 | L35: 32500 | M35: 302500 | N35: 32500 | O35: 302500 | P35: 32500 | Q35: 302500 | R35: 32500 | S35: 302500 | T35: 32500 | U35: 302500 | V35: 32500 | W35: 302500 | X35: 32500 | Y35: 302500 | Z35: 32500 | AA35: 302500 | AB35: 32500 | AC35: =+C35-E35-G35-I35-K35-M35-O35-Q35-S35-U35-W35-Y35-AA35 -> 907500 | AD35: =+D35-F35-H35-J35-L35-N35-P35-R35-T35-V35-X35-Z35-AB35 -> 97500 | AE35: =F35+H35+J35+L35+N35+P35+R35+T35+V35+X35+Z35+AB35 -> 292500
A36: 34000643 | B36: M Ridwan | C36: 2299000 | D36: 341000 | K36: 191583.33 | L36: 28416.667 | M36: 191583.33 | N36: 28416.667 | O36: 191583.33 | P36: 28416.667 | Q36: 191583.33 | R36: 28416.667 | S36: 191583.33 | T36: 28416.667 | U36: 191583.33 | V36: 28416.667 | W36: 191583.33 | X36: 28416.667 | Y36: 191583.33 | Z36: 28416.667 | AA36: 191583.33 | AB36: 28416.667 | AC36: =+C36-E36-G36-I36-K36-M36-O36-Q36-S36-U36-W36-Y36-AA36 -> 574750 | AD36: =+D36-F36-H36-J36-L36-N36-P36-R36-T36-V36-X36-Z36-AB36 -> 85250 | AE36: =F36+H36+J36+L36+N36+P36+R36+T36+V36+X36+Z36+AB36 -> 255750
A37: 34000397 | B37: Aris Suprayogi | C37: 3000000 | D37: 420000 | K37: 250000 | L37: 35000 | M37: 250000 | N37: 35000 | O37: 250000 | P37: 35000 | Q37: 250000 | R37: 35000 | S37: 250000 | T37: 35000 | U37: 250000 | V37: 35000 | W37: 250000 | X37: 35000 | Y37: 250000 | Z37: 35000 | AA37: 250000 | AB37: 35000 | AC37: =+C37-E37-G37-I37-K37-M37-O37-Q37-S37-U37-W37-Y37-AA37 -> 750000 | AD37: =+D37-F37-H37-J37-L37-N37-P37-R37-T37-V37-X37-Z37-AB37 -> 105000 | AE37: =F37+H37+J37+L37+N37+P37+R37+T37+V37+X37+Z37+AB37 -> 315000
A38: 34000415 | B38: Asep Nurdin Kusdian | C38: 8000000 | D38: 940000 | K38: 666666.67 | L38: 78333.333 | M38: 666666.67 | N38: 78333.333 | O38: 666666.67 | P38: 78333.333 | Q38: 666666.67 | R38: 78333.333 | S38: 666666.67 | T38: 78333.333 | U38: 666666.67 | V38: 78333.333 | W38: 666666.67 | X38: 78333.333 | Y38: 666666.67 | Z38: 78333.333 | AA38: 666666.67 | AB38: 78333.333 | AC38: =+C38-E38-G38-I38-K38-M38-O38-Q38-S38-U38-W38-Y38-AA38 -> 2000000 | AD38: =+D38-F38-H38-J38-L38-N38-P38-R38-T38-V38-X38-Z38-AB38 -> 235000 | AE38: =F38+H38+J38+L38+N38+P38+R38+T38+V38+X38+Z38+AB38 -> 705000
A39: 34000363 | B39: Redi | C39: 2325000 | D39: 225000 | K39: 232500 | L39: 22500 | M39: 232500 | N39: 22500 | O39: 232500 | P39: 22500 | Q39: 232500 | R39: 22500 | S39: 232500 | T39: 22500 | U39: 232500 | V39: 22500 | W39: 232500 | X39: 22500 | Y39: 232500 | Z39: 22500 | AA39: 232500 | AB39: 22500 | AC39: =+C39-E39-G39-I39-K39-M39-O39-Q39-S39-U39-W39-Y39-AA39 -> 232500 | AD39: =+D39-F39-H39-J39-L39-N39-P39-R39-T39-V39-X39-Z39-AB39 -> 22500 | AE39: =F39+H39+J39+L39+N39+P39+R39+T39+V39+X39+Z39+AB39 -> 202500
A40: 34000534 | B40: Rio | C40: 3799000 | D40: 341000 | K40: 316583.33 | L40: 28416.667 | M40: 316583.33 | N40: 28416.667 | O40: 316583.33 | P40: 28416.667 | Q40: 316583.33 | R40: 28416.667 | S40: 316583.33 | T40: 28416.667 | U40: 316583.33 | V40: 28416.667 | W40: 316583.33 | X40: 28416.667 | Y40: 316583.33 | Z40: 28416.667 | AA40: 316583.33 | AB40: 28416.667 | AC40: =+C40-E40-G40-I40-K40-M40-O40-Q40-S40-U40-W40-Y40-AA40 -> 949750 | AD40: =+D40-F40-H40-J40-L40-N40-P40-R40-T40-V40-X40-Z40-AB40 -> 85250 | AE40: =F40+H40+J40+L40+N40+P40+R40+T40+V40+X40+Z40+AB40 -> 255750
A41: 34000758 | B41: AHMAD SETIAWAN | C41: 3299000 | D41: 351000 | M41: 329900 | N41: 35100 | O41: 329900 | P41: 35100 | Q41: 329900 | R41: 35100 | S41: 329900 | T41: 35100 | U41: 329900 | V41: 35100 | W41: 329900 | X41: 35100 | Y41: 329900 | Z41: 35100 | AA41: 329900 | AB41: 35100 | AC41: =+C41-E41-G41-I41-K41-M41-O41-Q41-S41-U41-W41-Y41-AA41 -> 659800 | AD41: =+D41-F41-H41-J41-L41-N41-P41-R41-T41-V41-X41-Z41-AB41 -> 70200 | AE41: =F41+H41+J41+L41+N41+P41+R41+T41+V41+X41+Z41+AB41 -> 280800
A42: 34000215 | B42: Candra Warsita | C42: 5600000 | D42: 400000 | M42: 466666.67 | N42: 33333.333 | O42: 466666.67 | P42: 33333.333 | Q42: 466666.67 | R42: 33333.333 | S42: 466666.67 | T42: 33333.333 | U42: 466666.67 | V42: 33333.333 | W42: 466666.67 | X42: 33333.333 | Y42: 466666.67 | Z42: 33333.333 | AA42: 466666.67 | AB42: 33333.333 | AC42: =+C42-E42-G42-I42-K42-M42-O42-Q42-S42-U42-W42-Y42-AA42 -> 1866666.7 | AD42: =+D42-F42-H42-J42-L42-N42-P42-R42-T42-V42-X42-Z42-AB42 -> 133333.33 | AE42: =F42+H42+J42+L42+N42+P42+R42+T42+V42+X42+Z42+AB42 -> 266666.67
A43: 34000462 | B43: Pramono | C43: 3999000 | D43: 441000 | S43: 333250 | T43: 36750 | U43: 333250 | V43: 36750 | W43: 333250 | X43: 36750 | Y43: 333250 | Z43: 36750 | AA43: 333250 | AB43: 36750 | AC43: =+C43-E43-G43-I43-K43-M43-O43-Q43-S43-U43-W43-Y43-AA43 -> 2332750 | AD43: =+D43-F43-H43-J43-L43-N43-P43-R43-T43-V43-X43-Z43-AB43 -> 257250 | AE43: =F43+H43+J43+L43+N43+P43+R43+T43+V43+X43+Z43+AB43 -> 183750
A44: 34000012 | B44: Wahidin | C44: 1000000 | D44: 125000 | U44: 111111.11 | V44: 13888.889 | W44: 111111.11 | X44: 13888.889 | Y44: 111111.11 | Z44: 13888.889 | AA44: 111111.11 | AB44: 13888.889 | AC44: =+C44-E44-G44-I44-K44-M44-O44-Q44-S44-U44-W44-Y44-AA44 -> 555555.56 | AD44: =+D44-F44-H44-J44-L44-N44-P44-R44-T44-V44-X44-Z44-AB44 -> 69444.444 | AE44: =F44+H44+J44+L44+N44+P44+R44+T44+V44+X44+Z44+AB44 -> 55555.556
A45: 34000119 | B45: ASEP PERMANA | C45: 3199000 | D45: 401000 | U45: 319900 | V45: 40100 | W45: 319900 | X45: 40100 | Y45: 319900 | Z45: 40100 | AA45: 319900 | AB45: 40100 | AC45: =+C45-E45-G45-I45-K45-M45-O45-Q45-S45-U45-W45-Y45-AA45 -> 1919400 | AD45: =+D45-F45-H45-J45-L45-N45-P45-R45-T45-V45-X45-Z45-AB45 -> 240600 | AE45: =F45+H45+J45+L45+N45+P45+R45+T45+V45+X45+Z45+AB45 -> 160400
A46: 34000469 | B46: JULI AGUS | C46: 3199000 | D46: 401000 | U46: 319900 | V46: 40100 | W46: 319900 | X46: 40100 | Y46: 319900 | Z46: 40100 | AA46: 319900 | AB46: 40100 | AC46: =+C46-E46-G46-I46-K46-M46-O46-Q46-S46-U46-W46-Y46-AA46 -> 1919400 | AD46: =+D46-F46-H46-J46-L46-N46-P46-R46-T46-V46-X46-Z46-AB46 -> 240600 | AE46: =F46+H46+J46+L46+N46+P46+R46+T46+V46+X46+Z46+AB46 -> 160400
A47: 34000394 | B47: FAJAR HARDIYANTO | C47: 3199000 | D47: 401000 | U47: 319900 | V47: 40100 | W47: 319900 | X47: 40100 | Y47: 319900 | Z47: 40100 | AA47: 319900 | AB47: 40100 | AC47: =+C47-E47-G47-I47-K47-M47-O47-Q47-S47-U47-W47-Y47-AA47 -> 1919400 | AD47: =+D47-F47-H47-J47-L47-N47-P47-R47-T47-V47-X47-Z47-AB47 -> 240600 | AE47: =F47+H47+J47+L47+N47+P47+R47+T47+V47+X47+Z47+AB47 -> 160400
A48: 34000257 | B48: BUDI SEPTIYADI | C48: 4999000 | D48: 641000 | U48: 416583.33 | V48: 53416.667 | W48: 416583.33 | X48: 53416.667 | Y48: 416583.33 | Z48: 53416.667 | AA48: 416583.33 | AB48: 53416.667 | AC48: =+C48-E48-G48-I48-K48-M48-O48-Q48-S48-U48-W48-Y48-AA48 -> 3332666.7 | AD48: =+D48-F48-H48-J48-L48-N48-P48-R48-T48-V48-X48-Z48-AB48 -> 427333.33 | AE48: =F48+H48+J48+L48+N48+P48+R48+T48+V48+X48+Z48+AB48 -> 213666.67
A49: 34000405 | B49: SURYADI | C49: 2000000 | D49: 280000 | U49: 166666.67 | V49: 23333.333 | W49: 166666.67 | X49: 23333.333 | Y49: 166666.67 | Z49: 23333.333 | AA49: 166666.67 | AB49: 23333.333 | AC49: =+C49-E49-G49-I49-K49-M49-O49-Q49-S49-U49-W49-Y49-AA49 -> 1333333.3 | AD49: =+D49-F49-H49-J49-L49-N49-P49-R49-T49-V49-X49-Z49-AB49 -> 186666.67 | AE49: =F49+H49+J49+L49+N49+P49+R49+T49+V49+X49+Z49+AB49 -> 93333.333
A50: 34000670 | B50: ASEP GUNAWAN | C50: 3999000 | D50: 401000 | U50: 399900 | V50: 40100 | W50: 399900 | X50: 40100 | Y50: 399900 | Z50: 40100 | AA50: 399900 | AB50: 40100 | AC50: =+C50-E50-G50-I50-K50-M50-O50-Q50-S50-U50-W50-Y50-AA50 -> 2399400 | AD50: =+D50-F50-H50-J50-L50-N50-P50-R50-T50-V50-X50-Z50-AB50 -> 240600 | AE50: =F50+H50+J50+L50+N50+P50+R50+T50+V50+X50+Z50+AB50 -> 160400
A51: 34000771 | B51: RONI IRAWAN | C51: 2999000 | D51: 331000 | W51: 499833.33 | X51: 55166.667 | Y51: 499833.33 | Z51: 55166.667 | AA51: 499833.33 | AB51: 55166.667 | AC51: =+C51-E51-G51-I51-K51-M51-O51-Q51-S51-U51-W51-Y51-AA51 -> 1499500 | AD51: =+D51-F51-H51-J51-L51-N51-P51-R51-T51-V51-X51-Z51-AB51 -> 165500 | AE51: =F51+H51+J51+L51+N51+P51+R51+T51+V51+X51+Z51+AB51 -> 165500
A52: 34000277 | B52: YUDI WAHYUDIN | C52: 1999000 | D52: 226000 | W52: 399800 | X52: 45200 | Y52: 399800 | Z52: 45200 | AA52: 399800 | AB52: 45200 | AC52: =+C52-E52-G52-I52-K52-M52-O52-Q52-S52-U52-W52-Y52-AA52 -> 799600 | AD52: =+D52-F52-H52-J52-L52-N52-P52-R52-T52-V52-X52-Z52-AB52 -> 90400 | AE52: =F52+H52+J52+L52+N52+P52+R52+T52+V52+X52+Z52+AB52 -> 135600
A53: 34000446 | B53: MARKUWAT | C53: 3000000 | D53: 300000 | W53: 300000 | X53: 30000 | Y53: 300000 | Z53: 30000 | AA53: 300000 | AB53: 30000 | AC53: =+C53-E53-G53-I53-K53-M53-O53-Q53-S53-U53-W53-Y53-AA53 -> 2100000 | AD53: =+D53-F53-H53-J53-L53-N53-P53-R53-T53-V53-X53-Z53-AB53 -> 210000 | AE53: =F53+H53+J53+L53+N53+P53+R53+T53+V53+X53+Z53+AB53 -> 90000
A54: 34000012 | B54: Wahidin | C54: 750000 | D54: 75000 | Y54: 250000 | Z54: 25000 | AA54: 500000 | AB54: 50000 | AC54: =+C54-E54-G54-I54-K54-M54-O54-Q54-S54-U54-W54-Y54-AA54 -> 0 | AD54: =+D54-F54-H54-J54-L54-N54-P54-R54-T54-V54-X54-Z54-AB54 -> 0 | AE54: =F54+H54+J54+L54+N54+P54+R54+T54+V54+X54+Z54+AB54 -> 75000
A55: 34000453 | B55: Agus Mulyadi | C55: 6265750 | D55: 634250 | Y55: 522145.83 | Z55: 52854.167 | AA55: 522145.83 | AB55: 52854.167 | AC55: =+C55-E55-G55-I55-K55-M55-O55-Q55-S55-U55-W55-Y55-AA55 -> 5221458.3 | AD55: =+D55-F55-H55-J55-L55-N55-P55-R55-T55-V55-X55-Z55-AB55 -> 528541.67 | AE55: =F55+H55+J55+L55+N55+P55+R55+T55+V55+X55+Z55+AB55 -> 105708.33
A56: 34000388 | B56: ANDRIAN PERMANA | C56: 5500000 | D56: 550000 | AA56: 550000 | AB56: 55000 | AC56: =+C56-E56-G56-I56-K56-M56-O56-Q56-S56-U56-W56-Y56-AA56 -> 4950000 | AD56: =+D56-F56-H56-J56-L56-N56-P56-R56-T56-V56-X56-Z56-AB56 -> 495000 | AE56: =F56+H56+J56+L56+N56+P56+R56+T56+V56+X56+Z56+AB56 -> 55000
A57: 34000012 | B57: Wahidin | C57: 2000000 | D57: 220000 | AA57: 166666.67 | AB57: 18333.333 | AC57: =+C57-E57-G57-I57-K57-M57-O57-Q57-S57-U57-W57-Y57-AA57 -> 1833333.3 | AD57: =+D57-F57-H57-J57-L57-N57-P57-R57-T57-V57-X57-Z57-AB57 -> 201666.67 | AE57: =F57+H57+J57+L57+N57+P57+R57+T57+V57+X57+Z57+AB57 -> 18333.333
A58: 34000518 | B58: Rizky Kusumayadi | C58: 7000000 | D58: 704000 | AA58: 583333.33 | AB58: 58666.667 | AC58: =+C58-E58-G58-I58-K58-M58-O58-Q58-S58-U58-W58-Y58-AA58 -> 6416666.7 | AD58: =+D58-F58-H58-J58-L58-N58-P58-R58-T58-V58-X58-Z58-AB58 -> 645333.33 | AE58: =F58+H58+J58+L58+N58+P58+R58+T58+V58+X58+Z58+AB58 -> 58666.667
A59: 34000354 | B59: Ahmad Suwarna | C59: 4200000 | D59: 420000 | AC59: =+C59-E59-G59-I59-K59-M59-O59-Q59-S59-U59-W59-Y59-AA59 -> 4200000 | AD59: =+D59-F59-H59-J59-L59-N59-P59-R59-T59-V59-X59-Z59-AB59 -> 420000 | AE59: =F59+H59+J59+L59+N59+P59+R59+T59+V59+X59+Z59+AB59 -> 0
A60: 34000379 | B60: Januar Muharna | C60: 10000000 | D60: 1130000 | AC60: =+C60-E60-G60-I60-K60-M60-O60-Q60-S60-U60-W60-Y60-AA60 -> 10000000 | AD60: =+D60-F60-H60-J60-L60-N60-P60-R60-T60-V60-X60-Z60-AB60 -> 1130000 | AE60: =F60+H60+J60+L60+N60+P60+R60+T60+V60+X60+Z60+AB60 -> 0
AC61: =+C61-E61-G61-I61-K61-M61-O61-Q61-S61-U61-W61-Y61-AA61 -> 0 | AD61: =+D61-F61-H61-J61-L61-N61-P61-R61-T61-V61-X61-Z61-AB61 -> 0
A62: TOTAL | C62: =SUM(C28:C61) -> 1.2042342e+08 | D62: =SUM(D28:D61) -> 13698583 | E62: =SUM(E28:E61) -> 433333.33 | F62: =SUM(F28:F61) -> 64666.667 | G62: =SUM(G28:G61) -> 433333.33 | H62: =SUM(H28:H61) -> 64666.667 | I62: =SUM(I28:I61) -> 1229800.3 | J62: =SUM(J28:J61) -> 177699.67 | ... AD62: =SUM(AD28:AD61) -> 6982156.1
D64: Total Pelunasan Pokok 2021 | G64: =E62+G62+I62+K62+M62+O62+Q62+S62+U62+W62+Y62+AA62 -> 56958573
D65: Total Pendapatan Jasa Pengadaan 2021 | G65: =F62+H62+J62+L62+N62+P62+R62+T62+V62+X62+Z62+AB62 -> 6716427.2 | AA65: Saldo Kas | AB65: 6733585
AA66: Pitang | AB66: =AC62 -> 63464843
D68: Cash On Hand | E68: 6733585
D69: AR | E69: =AC62 -> 63464843
E70: =G65 -> 6716427.2
A73: AEROSPACE
A74: KARTU ANGSURAN PENGADAAN KOPERASI KARYAWAN
A75: TAHUN 2022
A76: No.Kontrak | B76: NAMA KARYAWAN | C76: Harga Beli | D76: Keuntungan | E76: ANGSURAN | AC76: SALDO
E77: JAN | G77: FEB | I77: MAR | K77: APR | M77: MEI | O77: JUN | Q77: JUL | S77: AGT | U77: SEP | W77: OKT | Y77: NOV | AA77: DES
E78: Pokok | F78: Bunga | G78: Pokok | H78: Bunga | I78: Pokok | J78: Bunga | K78: Pokok | L78: Bunga | M78: Pokok | N78: Bunga | O78: Pokok | P78: Bunga | Q78: Pokok | R78: Bunga | S78: Pokok | T78: Bunga | U78: Pokok | V78: Bunga | W78: Pokok | X78: Bunga | Y78: Pokok | Z78: Bunga | AA78: Pokok | AB78: Bunga | AC78: Pokok | AD78: Bunga
A79: 34000118 | B79: Syswahyudi | C79: =AC28 -> 1.1641532e-10 | D79: =AD28 -> 1.4551915e-11 | AC79: =+C79-E79-G79-I79-K79-M79-O79-Q79-S79-U79-W79-Y79-AA79 -> 1.1641532e-10 | AD79: =+D79-F79-H79-J79-L79-N79-P79-R79-T79-V79-X79-Z79-AB79 -> 1.4551915e-11 | AE79: =F79+H79+J79+L79+N79+P79+R79+T79+V79+X79+Z79+AB79 -> 0
A80: 34000229 | B80: Erik Fujiwa | C80: =AC29 -> 333329 | D80: =AD29 -> 47670 | E80: 166667 | F80: 23333 | G80: 166667 | H80: 23333 | AC80: =+C80-E80-G80-I80-K80-M80-O80-Q80-S80-U80-W80-Y80-AA80 -> -5 | AD80: =+D80-F80-H80-J80-L80-N80-P80-R80-T80-V80-X80-Z80-AB80 -> 1004 | AE80: =F80+H80+J80+L80+N80+P80+R80+T80+V80+X80+Z80+AB80 -> 46666
A81: 34000379 | B81: Januar Muharna | C81: =AC30 -> 833333.33 | D81: =AD30 -> 111666.67 | Q81: 833333.33 | R81: 111666.67 | AC81: =+C81-E81-G81-I81-K81-M81-O81-Q81-S81-U81-W81-Y81-AA81 -> 0 | AD81: =+D81-F81-H81-J81-L81-N81-P81-R81-T81-V81-X81-Z81-AB81 -> 0 | AE81: =F81+H81+J81+L81+N81+P81+R81+T81+V81+X81+Z81+AB81 -> 111666.67
A82: 34000118 | B82: Syswahyudi | C82: =AC31 -> -3.4924597e-10 | D82: =AD31 -> -1.4551915e-11 | AC82: =+C82-E82-G82-I82-K82-M82-O82-Q82-S82-U82-W82-Y82-AA82 -> -3.4924597e-10 | AD82: =+D82-F82-H82-J82-L82-N82-P82-R82-T82-V82-X82-Z82-AB82 -> -1.4551915e-11 | AE82: =F82+H82+J82+L82+N82+P82+R82+T82+V82+X82+Z82+AB82 -> 0
A83: 34000351 | B83: Ari Rosandi | C83: =AC32 -> 0 | D83: =AD32 -> 0 | AC83: =+C83-E83-G83-I83-K83-M83-O83-Q83-S83-U83-W83-Y83-AA83 -> 0 | AD83: =+D83-F83-H83-J83-L83-N83-P83-R83-T83-V83-X83-Z83-AB83 -> 0 | AE83: =F83+H83+J83+L83+N83+P83+R83+T83+V83+X83+Z83+AB83 -> 0
A84: 34000203 | B84: Bonny Aries | C84: =AC33 -> 750000 | D84: =AD33 -> 99000 | E84: 250000 | F84: 33000 | G84: 250000 | H84: 33000 | I84: 250000 | J84: 33000 | AC84: =+C84-E84-G84-I84-K84-M84-O84-Q84-S84-U84-W84-Y84-AA84 -> 0 | AD84: =+D84-F84-H84-J84-L84-N84-P84-R84-T84-V84-X84-Z84-AB84 -> 0 | AE84: =F84+H84+J84+L84+N84+P84+R84+T84+V84+X84+Z84+AB84 -> 99000
A85: 34000514 | B85: Adifia Pramana | C85: =AC34 -> 874750 | D85: =AD34 -> 100250 | E85: 291583.33 | F85: 33416.667 | G85: 291583.33 | H85: 33416.667 | I85: 291583.33 | J85: 33416.667 | K85: 291583.33 | L85: 33416.667 | AC85: =+C85-E85-G85-I85-K85-M85-O85-Q85-S85-U85-W85-Y85-AA85 -> -291583.33 | AD85: =+D85-F85-H85-J85-L85-N85-P85-R85-T85-V85-X85-Z85-AB85 -> -33416.667 | AE85: =F85+H85+J85+L85+N85+P85+R85+T85+V85+X85+Z85+AB85 -> 133666.67
A86: 34000354 | B86: Ahmad Suwarna | C86: =AC35 -> 907500 | D86: =AD35 -> 97500 | E86: 302500 | F86: 32500 | G86: 302500 | H86: 32500 | I86: 302500 | J86: 32500 | K86: 302500 | L86: 32500 | AC86: =+C86-E86-G86-I86-K86-M86-O86-Q86-S86-U86-W86-Y86-AA86 -> -302500 | AD86: =+D86-F86-H86-J86-L86-N86-P86-R86-T86-V86-X86-Z86-AB86 -> -32500 | AE86: =F86+H86+J86+L86+N86+P86+R86+T86+V86+X86+Z86+AB86 -> 130000
A87: 34000643 | B87: M Ridwan | C87: =AC36 -> 574750 | D87: =AD36 -> 85250 | E87: 191583.33 | F87: 28416.667 | G87: 191583.33 | H87: 28416.667 | I87: 191583.33 | J87: 28416.667 | K87: 191583.33 | L87: 28416.667 | AC87: =+C87-E87-G87-I87-K87-M87-O87-Q87-S87-U87-W87-Y87-AA87 -> -191583.33 | AD87: =+D87-F87-H87-J87-L87-N87-P87-R87-T87-V87-X87-Z87-AB87 -> -28416.667 | AE87: =F87+H87+J87+L87+N87+P87+R87+T87+V87+X87+Z87+AB87 -> 113666.67
A88: 34000397 | B88: Aris Suprayogi | C88: =AC37 -> 750000 | D88: =AD37 -> 105000 | E88: 250000 | F88: 35000 | G88: 250000 | H88: 35000 | I88: 250000 | J88: 35000 | K88: 250000 | L88: 35000 | M88: 250000 | N88: 35000 | AC88: =+C88-E88-G88-I88-K88-M88-O88-Q88-S88-U88-W88-Y88-AA88 -> -500000 | AD88: =+D88-F88-H88-J88-L88-N88-P88-R88-T88-V88-X88-Z88-AB88 -> -70000 | AE88: =F88+H88+J88+L88+N88+P88+R88+T88+V88+X88+Z88+AB88 -> 175000
A89: 34000415 | B89: Asep Nurdin Kusdian | C89: =AC38 -> 2000000 | D89: =AD38 -> 235000 | E89: 666666.67 | F89: 78333.333 | G89: 666666.67 | H89: 78333.333 | I89: 666666.67 | J89: 78333.333 | K89: 666666.67 | L89: 78333.333 | M89: 666666.67 | N89: 78333.333 | AC89: =+C89-E89-G89-I89-K89-M89-O89-Q89-S89-U89-W89-Y89-AA89 -> -1333333.3 | AD89: =+D89-F89-H89-J89-L89-N89-P89-R89-T89-V89-X89-Z89-AB89 -> -156666.67 | AE89: =F89+H89+J89+L89+N89+P89+R89+T89+V89+X89+Z89+AB89 -> 391666.67
A90: 34000363 | B90: Redi | C90: =AC39 -> 232500 | D90: =AD39 -> 22500 | E90: 232500 | F90: 22500 | G90: 232500 | H90: 22500 | I90: 232500 | J90: 22500 | AC90: =+C90-E90-G90-I90-K90-M90-O90-Q90-S90-U90-W90-Y90-AA90 -> -465000 | AD90: =+D90-F90-H90-J90-L90-N90-P90-R90-T90-V90-X90-Z90-AB90 -> -45000 | AE90: =F90+H90+J90+L90+N90+P90+R90+T90+V90+X90+Z90+AB90 -> 67500
A91: 34000534 | B91: Rio | C91: =AC40 -> 949750 | D91: =AD40 -> 85250 | E91: 316583.33 | F91: 28416.667 | G91: 316583.33 | H91: 28416.667 | I91: 316583.33 | J91: 28416.667 | K91: 316583.33 | L91: 28416.667 | M91: 316583.33 | N91: 28416.667 | AC91: =+C91-E91-G91-I91-K91-M91-O91-Q91-S91-U91-W91-Y91-AA91 -> -633166.67 | AD91: =+D91-F91-H91-J91-L91-N91-P91-R91-T91-V91-X91-Z91-AB91 -> -56833.333 | AE91: =F91+H91+J91+L91+N91+P91+R91+T91+V91+X91+Z91+AB91 -> 142083.33
A92: 34000758 | B92: AHMAD SETIAWAN | C92: =AC41 -> 659800 | D92: =AD41 -> 70200 | E92: 329900 | F92: 35100 | G92: 329900 | H92: 35100 | I92: 329900 | J92: 35100 | K92: 329900 | L92: 35100 | AC92: =+C92-E92-G92-I92-K92-M92-O92-Q92-S92-U92-W92-Y92-AA92 -> -659800 | AD92: =+D92-F92-H92-J92-L92-N92-P92-R92-T92-V92-X92-Z92-AB92 -> -70200 | AE92: =F92+H92+J92+L92+N92+P92+R92+T92+V92+X92+Z92+AB92 -> 140400
A93: 34000215 | B93: Candra Warsita | C93: =AC42 -> 1866666.7 | D93: =AD42 -> 133333.33 | E93: 466666.67 | F93: 33333.333 | G93: 466666.67 | H93: 33333.333 | I93: 466666.67 | J93: 33333.333 | K93: 466666.67 | L93: 33333.333 | M93: 466666.67 | N93: 33333.333 | O93: 466666.67 | P93: 33333.333 | AC93: =+C93-E93-G93-I93-K93-M93-O93-Q93-S93-U93-W93-Y93-AA93 -> -933333.33 | AD93: =+D93-F93-H93-J93-L93-N93-P93-R93-T93-V93-X93-Z93-AB93 -> -66666.667 | AE93: =F93+H93+J93+L93+N93+P93+R93+T93+V93+X93+Z93+AB93 -> 200000
A94: 34000462 | B94: Pramono | C94: =AC43 -> 2332750 | D94: =AD43 -> 257250 | E94: 333250 | F94: 36750 | G94: 333250 | H94: 36750 | I94: 333250 | J94: 36750 | K94: 333250 | L94: 36750 | M94: 333250 | N94: 36750 | O94: 333250 | P94: 36750 | Q94: 333250 | R94: 36750 | AC94: =+C94-E94-G94-I94-K94-M94-O94-Q94-S94-U94-W94-Y94-AA94 -> 0 | AD94: =+D94-F94-H94-J94-L94-N94-P94-R94-T94-V94-X94-Z94-AB94 -> 0 | AE94: =F94+H94+J94+L94+N94+P94+R94+T94+V94+X94+Z94+AB94 -> 257250
A95: 34000012 | B95: Wahidin | C95: =AC44 -> 555555.56 | D95: =AD44 -> 69444.444 | E95: 111111.11 | F95: 13888.889 | G95: 111111.11 | H95: 13888.889 | I95: 111111.11 | J95: 13888.889 | K95: 111111.11 | L95: 13888.889 | M95: 111111.11 | N95: 13888.889 | AC95: =+C95-E95-G95-I95-K95-M95-O95-Q95-S95-U95-W95-Y95-AA95 -> -8.7311491e-11 | AD95: =+D95-F95-H95-J95-L95-N95-P95-R95-T95-V95-X95-Z95-AB95 -> -1.0913936e-11 | AE95: =F95+H95+J95+L95+N95+P95+R95+T95+V95+X95+Z95+AB95 -> 69444.444
A96: 34000119 | B96: ASEP PERMANA | C96: =AC45 -> 1919400 | D96: =AD45 -> 240600 | E96: 319900 | F96: 40100 | G96: 319900 | H96: 40100 | I96: 319900 | J96: 40100 | K96: 319900 | L96: 40100 | M96: 319900 | N96: 40100 | O96: 319900 | P96: 40100 | Q96: 319900 | R96: 40100 | S96: 319900 | T96: 40100 | AC96: =+C96-E96-G96-I96-K96-M96-O96-Q96-S96-U96-W96-Y96-AA96 -> -639800 | AD96: =+D96-F96-H96-J96-L96-N96-P96-R96-T96-V96-X96-Z96-AB96 -> -80200 | AE96: =F96+H96+J96+L96+N96+P96+R96+T96+V96+X96+Z96+AB96 -> 320800
A97: 34000469 | B97: JULI AGUS | C97: =AC46 -> 1919400 | D97: =AD46 -> 240600 | E97: 319900 | F97: 40100 | G97: 319900 | H97: 40100 | I97: 319900 | J97: 40100 | K97: 319900 | L97: 40100 | M97: 319900 | N97: 40100 | O97: 319900 | P97: 40100 | Q97: 319900 | R97: 40100 | S97: 319900 | T97: 40100 | AC97: =+C97-E97-G97-I97-K97-M97-O97-Q97-S97-U97-W97-Y97-AA97 -> -639800 | AD97: =+D97-F97-H97-J97-L97-N97-P97-R97-T97-V97-X97-Z97-AB97 -> -80200 | AE97: =F97+H97+J97+L97+N97+P97+R97+T97+V97+X97+Z97+AB97 -> 320800
A98: 34000394 | B98: FAJAR HARDIYANTO | C98: =AC47 -> 1919400 | D98: =AD47 -> 240600 | E98: 319900 | F98: 40100 | G98: 319900 | H98: 40100 | I98: 319900 | J98: 40100 | K98: 319900 | L98: 40100 | M98: 319900 | N98: 40100 | O98: 319900 | P98: 40100 | Q98: 319900 | R98: 40100 | S98: 319900 | T98: 40100 | AC98: =+C98-E98-G98-I98-K98-M98-O98-Q98-S98-U98-W98-Y98-AA98 -> -639800 | AD98: =+D98-F98-H98-J98-L98-N98-P98-R98-T98-V98-X98-Z98-AB98 -> -80200 | AE98: =F98+H98+J98+L98+N98+P98+R98+T98+V98+X98+Z98+AB98 -> 320800
A99: 34000257 | B99: BUDI SEPTIYADI | C99: =AC48 -> 3332666.7 | D99: =AD48 -> 427333.33 | E99: 416583.33 | F99: 53416.667 | G99: 416583.33 | H99: 53416.667 | I99: 416583.33 | J99: 53416.667 | K99: 416583.33 | L99: 53416.667 | M99: 416583.33 | N99: 53416.667 | O99: 416583.33 | P99: 53416.667 | Q99: 416583.33 | R99: 53416.667 | S99: 416583.33 | T99: 53416.667 | AC99: =+C99-E99-G99-I99-K99-M99-O99-Q99-S99-U99-W99-Y99-AA99 -> -1.1641532e-10 | AD99: =+D99-F99-H99-J99-L99-N99-P99-R99-T99-V99-X99-Z99-AB99 -> 1.4551915e-11 | AE99: =F99+H99+J99+L99+N99+P99+R99+T99+V99+X99+Z99+AB99 -> 427333.33
A100: 34000405 | B100: SURYADI | C100: =AC49 -> 1333333.3 | D100: =AD49 -> 186666.67 | E100: 166666.67 | F100: 23333.333 | G100: 166666.67 | H100: 23333.333 | I100: 166666.67 | J100: 23333.333 | K100: 166666.67 | L100: 23333.333 | M100: 166666.67 | N100: 23333.333 | O100: 166666.67 | P100: 23333.333 | Q100: 166666.67 | R100: 23333.333 | S100: 166666.67 | T100: 23333.333 | AC100: =+C100-E100-G100-I100-K100-M100-O100-Q100-S100-U100-W100-Y100-AA100 -> -1.7462298e-10 | AD100: =+D100-F100-H100-J100-L100-N100-P100-R100-T100-V100-X100-Z100-AB100 -> -3.6379788e-11 | AE100: =F100+H100+J100+L100+N100+P100+R100+T100+V100+X100+Z100+AB100 -> 186666.67
A101: 34000670 | B101: ASEP GUNAWAN | C101: =AC50 -> 2399400 | D101: =AD50 -> 240600 | E101: 399900 | F101: 40100 | G101: 399900 | H101: 40100 | I101: 399900 | J101: 40100 | K101: 399900 | L101: 40100 | M101: 399900 | N101: 40100 | O101: 399900 | P101: 40100 | AC101: =+C101-E101-G101-I101-K101-M101-O101-Q101-S101-U101-W101-Y101-AA101 -> 0 | AD101: =+D101-F101-H101-J101-L101-N101-P101-R101-T101-V101-X101-Z101-AB101 -> 0 | AE101: =F101+H101+J101+L101+N101+P101+R101+T101+V101+X101+Z101+AB101 -> 240600
A102: 34000771 | B102: RONI IRAWAN | C102: =AC51 -> 1499500 | D102: =AD51 -> 165500 | E102: 499833.33 | F102: 55166.667 | G102: 499833.33 | H102: 55166.667 | I102: 499833.33 | J102: 55166.667 | AC102: =+C102-E102-G102-I102-K102-M102-O102-Q102-S102-U102-W102-Y102-AA102 -> 1.1641532e-10 | AD102: =+D102-F102-H102-J102-L102-N102-P102-R102-T102-V102-X102-Z102-AB102 -> 1.4551915e-11 | AE102: =F102+H102+J102+L102+N102+P102+R102+T102+V102+X102+Z102+AB102 -> 165500
A103: 34000277 | B103: YUDI WAHYUDIN | C103: =AC52 -> 799600 | D103: =AD52 -> 90400 | E103: 399800 | F103: 45200 | G103: 399800 | H103: 45200 | AC103: =+C103-E103-G103-I103-K103-M103-O103-Q103-S103-U103-W103-Y103-AA103 -> 0 | AD103: =+D103-F103-H103-J103-L103-N103-P103-R103-T103-V103-X103-Z103-AB103 -> 0 | AE103: =F103+H103+J103+L103+N103+P103+R103+T103+V103+X103+Z103+AB103 -> 90400
A104: 34000446 | B104: MARKUWAT | C104: =AC53 -> 2100000 | D104: =AD53 -> 210000 | E104: 300000 | F104: 30000 | G104: 300000 | H104: 30000 | I104: 300000 | J104: 30000 | K104: 300000 | L104: 30000 | M104: 300000 | N104: 30000 | O104: 300000 | P104: 30000 | Q104: 300000 | R104: 30000 | AC104: =+C104-E104-G104-I104-K104-M104-O104-Q104-S104-U104-W104-Y104-AA104 -> 0 | AD104: =+D104-F104-H104-J104-L104-N104-P104-R104-T104-V104-X104-Z104-AB104 -> 0 | AE104: =F104+H104+J104+L104+N104+P104+R104+T104+V104+X104+Z104+AB104 -> 210000
A105: 34000012 | B105: Wahidin | C105: =AC54 -> 0 | D105: =AD54 -> 0 | AC105: =+C105-E105-G105-I105-K105-M105-O105-Q105-S105-U105-W105-Y105-AA105 -> 0 | AD105: =+D105-F105-H105-J105-L105-N105-P105-R105-T105-V105-X105-Z105-AB105 -> 0 | AE105: =F105+H105+J105+L105+N105+P105+R105+T105+V105+X105+Z105+AB105 -> 0
A106: 34000453 | B106: Agus Mulyadi | C106: =AC55 -> 5221458.3 | D106: =AD55 -> 528541.67 | E106: 522145.83 | F106: 52854.167 | G106: 522145.83 | H106: 52854.167 | I106: 522145.83 | J106: 52854.167 | K106: 522145.83 | L106: 52854.167 | M106: 522145.83 | N106: 52854.167 | O106: 522145.83 | P106: 52854.167 | Q106: 522145.83 | R106: 52854.167 | S106: 522145.83 | T106: 52854.167 | U106: 522145.83 | V106: 52854.167 | W106: 522145.83 | X106: 52854.167 | AC106: =+C106-E106-G106-I106-K106-M106-O106-Q106-S106-U106-W106-Y106-AA106 -> 5.8207661e-10 | AD106: =+D106-F106-H106-J106-L106-N106-P106-R106-T106-V106-X106-Z106-AB106 -> 1.4551915e-11 | AE106: =F106+H106+J106+L106+N106+P106+R106+T106+V106+X106+Z106+AB106 -> 528541.67
A107: 34000388 | B107: ANDRIAN PERMANA | C107: =AC56 -> 4950000 | D107: =AD56 -> 495000 | E107: 550000 | F107: 55000 | G107: 550000 | H107: 55000 | I107: 550000 | J107: 55000 | K107: 550000 | L107: 55000 | M107: 550000 | N107: 55000 | O107: 550000 | P107: 55000 | Q107: 550000 | R107: 55000 | S107: 550000 | T107: 55000 | U107: 550000 | V107: 55000 | AC107: =+C107-E107-G107-I107-K107-M107-O107-Q107-S107-U107-W107-Y107-AA107 -> 0 | AD107: =+D107-F107-H107-J107-L107-N107-P107-R107-T107-V107-X107-Z107-AB107 -> 0 | AE107: =F107+H107+J107+L107+N107+P107+R107+T107+V107+X107+Z107+AB107 -> 495000
A108: 34000012 | B108: Wahidin | C108: =AC57 -> 1833333.3 | D108: =AD57 -> 201666.67 | E108: 166666.67 | F108: 18333.333 | G108: 166666.67 | H108: 18333.333 | I108: 166666.67 | J108: 18333.333 | K108: 166666.67 | L108: 18333.333 | M108: 166666.67 | N108: 18333.333 | O108: 166666.67 | P108: 18333.333 | Q108: 166666.67 | R108: 18333.333 | S108: =Q108*4 -> 666666.67 | T108: =R108*4 -> 73333.333 | AC108: =+C108-E108-G108-I108-K108-M108-O108-Q108-S108-U108-W108-Y108-AA108 -> -2.3283064e-10 | AD108: =+D108-F108-H108-J108-L108-N108-P108-R108-T108-V108-X108-Z108-AB108 -> -1.4551915e-11 | AE108: =F108+H108+J108+L108+N108+P108+R108+T108+V108+X108+Z108+AB108 -> 201666.67
...

Sheet  usp (dian)
A1: NPP | B1: Nama Anggota | C1: Total Pokok | D1: Total Jasa | E1: Total Invoice 2025
A2: 34000004 | B2: YAYA CAHRIA | C2: 0 | D2: 1200000 | E2: =SUM(C2:D2) -> 1200000 | F2: 1200000 | G2: =D2=F2 -> TRUE | H2: =VLOOKUP(A2,'Distribusi SHU'!C:C,1,0) -> 34000004 | I2: =A2=H2 -> TRUE | K2: 34000484 | L2: UDAN HERNAWAN | M2: =VLOOKUP(K2,'Distribusi SHU'!C:I,7,0) -> 1410000
A3: 34000009 | B3: TRI HARTANTO | C3: 0 | D3: 1680000 | E3: =SUM(C3:D3) -> 1680000 | F3: 1680000 | G3: =D3=F3 -> TRUE | H3: =VLOOKUP(A3,'Distribusi SHU'!C:C,1,0) -> 34000009 | I3: =A3=H3 -> TRUE | K3: 34000653 | L3: EGY HERYANTO | M3: =VLOOKUP(K3,'Distribusi SHU'!C:I,7,0) -> 1920000
A4: 34000012 | B4: WAHIDIN | C4: 0 | D4: 746666.67 | E4: =SUM(C4:D4) -> 746666.67 | F4: 746666.67 | G4: =D4=F4 -> TRUE | H4: =VLOOKUP(A4,'Distribusi SHU'!C:C,1,0) -> 34000012 | I4: =A4=H4 -> TRUE | K4: 34000570 | L4: ADE ASMI TRIYOSO | M4: =VLOOKUP(K4,'Distribusi SHU'!C:I,7,0) -> 1116000
A5: 34000027 | B5: BUDI DAMHUDI | C5: 0 | D5: 1050000 | E5: =SUM(C5:D5) -> 1050000 | F5: 1050000 | G5: =D5=F5 -> TRUE | H5: =VLOOKUP(A5,'Distribusi SHU'!C:C,1,0) -> 34000027 | I5: =A5=H5 -> TRUE | K5: 34000203 | L5: BONNY ARIES | M5: =VLOOKUP(K5,'Distribusi SHU'!C:I,7,0) -> 1035000
A6: 34000049 | B6: KIKI KRISE | C6: 0 | D6: 1050000 | E6: =SUM(C6:D6) -> 1050000 | F6: 1050000 | G6: =D6=F6 -> TRUE | H6: =VLOOKUP(A6,'Distribusi SHU'!C:C,1,0) -> 34000049 | I6: =A6=H6 -> TRUE | K6: 34000004 | L6: YAYA CAHRIA | M6: =VLOOKUP(K6,'Distribusi SHU'!C:I,7,0) -> 1200000
A7: 34000050 | B7: HERI GUNAWAN | C7: 0 | D7: 1050000 | E7: =SUM(C7:D7) -> 1050000 | F7: 1050000 | G7: =D7=F7 -> TRUE | H7: =VLOOKUP(A7,'Distribusi SHU'!C:C,1,0) -> 34000050 | I7: =A7=H7 -> TRUE | K7: 34000692 | L7: IMAM NURZAMAN | M7: =VLOOKUP(K7,'Distribusi SHU'!C:I,7,0) -> 2210000
A8: 34000060 | B8: AMIN | C8: 0 | D8: 2247500 | E8: =SUM(C8:D8) -> 2247500 | F8: 2247500 | G8: =D8=F8 -> TRUE | H8: =VLOOKUP(A8,'Distribusi SHU'!C:C,1,0) -> 34000060 | I8: =A8=H8 -> TRUE | K8: 34000514 | L8: ADIFIA PRAMANA | M8: =VLOOKUP(K8,'Distribusi SHU'!C:I,7,0) -> 1530000
A9: 34000067 | B9: SOFYAN AHMAD | C9: 0 | D9: 840000 | E9: =SUM(C9:D9) -> 840000 | F9: 840000 | G9: =D9=F9 -> TRUE | H9: =VLOOKUP(A9,'Distribusi SHU'!C:C,1,0) -> 34000067 | I9: =A9=H9 -> TRUE | K9: 34000510 | L9: GALIH PRASETYO | M9: =VLOOKUP(K9,'Distribusi SHU'!C:I,7,0) -> 888000
A10: 34000074 | B10: UJANG SOMANTRI | C10: 0 | D10: 594000 | E10: =SUM(C10:D10) -> 594000 | F10: 594000 | G10: =D10=F10 -> TRUE | H10: =VLOOKUP(A10,'Distribusi SHU'!C:C,1,0) -> 34000074 | I10: =A10=H10 -> TRUE | K10: 34000469 | L10: JULI AGUS SETIAWAN | M10: =VLOOKUP(K10,'Distribusi SHU'!C:I,7,0) -> 1050000
A11: 34000077 | B11: DENI SUHENDAR | C11: 0 | D11: 1050000 | E11: =SUM(C11:D11) -> 1050000 | F11: 1050000 | G11: =D11=F11 -> TRUE | H11: =VLOOKUP(A11,'Distribusi SHU'!C:C,1,0) -> 34000077 | I11: =A11=H11 -> TRUE | K11: 34000346 | L11: IRAWAN JUMYATI | M11: =VLOOKUP(K11,'Distribusi SHU'!C:I,7,0) -> 1145833.3
A12: 34000094 | B12: TRIBUDI YUDHA SANTOSO | C12: 0 | D12: 1244166.7 | E12: =SUM(C12:D12) -> 1244166.7 | F12: 1244166.7 | G12: =D12=F12 -> TRUE | H12: =VLOOKUP(A12,'Distribusi SHU'!C:C,1,0) -> 34000094 | I12: =A12=H12 -> TRUE | K12: 34000320 | L12: ASEP IPAN SOPIAN | M12: =VLOOKUP(K12,'Distribusi SHU'!C:I,7,0) -> 1350000
A13: 34000096 | B13: AGNI IKANOV | C13: 0 | D13: 1420000 | E13: =SUM(C13:D13) -> 1420000 | F13: 1420000 | G13: =D13=F13 -> TRUE | H13: =VLOOKUP(A13,'Distribusi SHU'!C:C,1,0) -> 34000096 | I13: =A13=H13 -> TRUE | K13: 34000625 | L13: ARIYANTO | M13: =VLOOKUP(K13,'Distribusi SHU'!C:I,7,0) -> 1050000
... A168: 34000862 | B168: DIKA TAUFIK | C168: 0 | D168: 962500 | E168: =SUM(C168:D168) -> 962500 | F168: 962500 | G168: =D168=F168 -> TRUE | H168: =VLOOKUP(A168,'Distribusi SHU'!C:C,1,0) -> 34000862 | I168: =A168=H168 -> TRUE | K168: 34000927 | L168: SUKMA ERZA AKBAR NUGRAHA | M168: =VLOOKUP(K168,'Distribusi SHU'!C:I,7,0) -> 614166.67
A169: 34000895 | B169: GIA ANGGARA | C169: =SUM(C2:C168) -> 0 | D169: 1088000 | E169: =SUM(C169:D169) -> 1088000 | F169: 1088000 | G169: =D169=F169 -> TRUE | H169: =VLOOKUP(A169,'Distribusi SHU'!C:C,1,0) -> 34000895 | I169: =A169=H169 -> TRUE | K169: 34000778 | L169: MUSTAFIDDUROHMAN FEBRYAN | M169: =VLOOKUP(K169,'Distribusi SHU'!C:I,7,0) -> 854166.67
A170: 34000927 | B170: SUKMA ERZA AKBAR NUGRAHA | C170: =SUM(C3:C169) -> 0 | D170: 614166.67 | E170: =SUM(C170:D170) -> 614166.67 | F170: 614166.67 | G170: =D170=F170 -> TRUE | H170: =VLOOKUP(A170,'Distribusi SHU'!C:C,1,0) -> 34000927 | I170: =A170=H170 -> TRUE | K170: 34000934 | L170: YOHANA SAEFUL MILAH | M170: =VLOOKUP(K170,'Distribusi SHU'!C:I,7,0) -> 240000
A171: 34000934 | B171: YOHANA SAEFUL MILAH | C171: =SUM(C4:C170) -> 0 | D171: 240000 | E171: =SUM(C171:D171) -> 240000 | F171: 240000 | G171: =D171=F171 -> TRUE | H171: =VLOOKUP(A171,'Distribusi SHU'!C:C,1,0) -> 34000934 | I171: =A171=H171 -> TRUE | K171: 34000605 | L171: SISWOYO SAMIN | M171: =VLOOKUP(K171,'Distribusi SHU'!C:I,7,0) -> 486000
A172: 34000949 | B172: SHENDY SURYADI | C172: =SUM(C5:C171) -> 0 | D172: 60000 | E172: =SUM(C172:D172) -> 60000 | F172: 60000 | G172: =D172=F172 -> TRUE | H172: =VLOOKUP(A172,'Distribusi SHU'!C:C,1,0) -> 34000949 | I172: =A172=H172 -> TRUE | K172: 34000273 | L172: ANANG ROHIMAT | M172: =VLOOKUP(K172,'Distribusi SHU'!C:I,7,0) -> 480000
A173: 34000962 | B173: ADHA FADHIL MOCHAMMAD | C173: =SUM(C6:C172) -> 0 | D173: 360000 | E173: =SUM(C173:D173) -> 360000 | F173: 360000 | G173: =D173=F173 -> TRUE | H173: =VLOOKUP(A173,'Distribusi SHU'!C:C,1,0) -> 34000962 | I173: =A173=H173 -> TRUE | K173: 34000962 | L173: ADHA FADHIL MOCHAMMAD | M173: =VLOOKUP(K173,'Distribusi SHU'!C:I,7,0) -> 360000
A174: 34000258 | B174: M. DIXIE PERMANA | C174: =SUM(C8:C173) -> 0 | D174: 1440000 | E174: =SUM(C174:D174) -> 1440000 | F174: 1440000 | G174: =D174=F174 -> TRUE | H174: =VLOOKUP(A174,'Distribusi SHU'!C:C,1,0) -> 34000258 | I174: =A174=H174 -> TRUE | K174: 34000067 | L174: SOFYAN AHMAD HIDAYAT | M174: =VLOOKUP(K174,'Distribusi SHU'!C:I,7,0) -> 840000
A175: 34000404 | B175: AHMAD SUPRIYADI | C175: =SUM(C9:C174) -> 0 | D175: 558333.33 | E175: =SUM(C175:D175) -> 558333.33 | F175: 558333.33 | G175: =D175=F175 -> TRUE | H175: =VLOOKUP(A175,'Distribusi SHU'!C:C,1,0) -> 34000404 | I175: =A175=H175 -> TRUE | K175: 34000949 | L175: SHENDY SURYADI | M175: =VLOOKUP(K175,'Distribusi SHU'!C:I,7,0) -> 60000
D176: =SUM(D2:D175) -> 2.1897239e+08 | E176: =SUM(C176:D176) -> 2.1897239e+08 | F176: =SUM(F2:F175) -> 2.1897239e+08

Sheet Toko
B1: Rekapitulasi Kas Toko
B2: Bulan | C2: Saldo Awal | D2: Pendapatan Toko | E2: Pendapatan Toko Dikurangi saldo awal | F2: Belanja Toko | G2: Beban Gaji | H2: Saldo Toko | I2: Saldo Toko
B3: 45292 | C3: 0 | D3: 195205976 | E3: =D3-C3 -> 195205976 | F3: 140358288 | G3: 4600000 | H3: =E3-F3-G3 -> 50247688 | I3: =D3-F3 -> 54847688 | O3: 4000000
B4: 45323 | C4: 54847688 | D4: 151745188 | E4: =D4-C4 -> 96897500 | F4: 92377514 | G4: 4280000 | H4: =E4-F4-G4 -> 239986 | I4: =D4-F4 -> 59367674 | O4: 4190000
B5: 45352 | C5: 59367674 | D5: 116080674 | E5: =D5-C5 -> 56713000 | F5: 52954367 | G5: 4740000 | H5: =E5-F5-G5 -> -981367 | I5: =D5-F5 -> 63126307 | O5: 3940000
B6: 45383 | C6: 63126307 | D6: 120236807 | E6: =D6-C6 -> 57110500 | F6: 41554955 | G6: 7280000 | H6: =E6-F6-G6 -> 8275545 | I6: =D6-F6 -> 78681852 | O6: 2602000
B7: 45413 | C7: 78487352 | D7: 173229248 | E7: =D7-C7 -> 94741896 | F7: 95568626 | G7: 3760000 | H7: =E7-F7-G7 -> -4586730 | I7: =D7-F7 -> 77660622 | O7: 4310000
B8: 45444 | C8: 77660622 | D8: 169112572 | E8: =D8-C8 -> 91451950 | F8: 78363961 | G8: 4000000 | H8: =E8-F8-G8 -> 9087989 | I8: =D8-F8 -> 90748611 | O8: 3930000
B9: 45474 | C9: 90471611 | D9: 209405311 | E9: =D9-C9 -> 118933700 | F9: 93807107 | G9: 3920000 | H9: =E9-F9-G9 -> 21206593 | I9: =D9-F9 -> 115598204 | K9: =F9-G9 -> 89887107 | O9: 4090000
B10: 45505 | C10: 115598204 | D10: 232615054 | E10: =D10-C10 -> 117016850 | F10: 102768760 | G10: 4710000 | H10: =E10-F10-G10 -> 9538090 | I10: =D10-F10 -> 129846294 | K10: =F10-G10 -> 98058760 | O10: 4260000
B11: 45536 | C11: 129846294 | D11: 234956894 | E11: =D11-C11 -> 105110600 | F11: 94028915 | G11: 4510000 | H11: =E11-F11-G11 -> 6571685 | I11: =D11-F11 -> 140927979 | K11: =F11-G11 -> 89518915 | O11: 4260000
B12: 45566 | C12: 140927979 | D12: 254238979 | E12: =D12-C12 -> 113311000 | F12: 110804577 | G12: 4940000 | H12: =E12-F12-G12 -> -2433577 | I12: =D12-F12 -> 143434402 | K12: =F12-G12 -> 105864577 | O12: 4280000
B13: 45597 | C13: 143263402 | D13: 259712052 | E13: =D13-C13 -> 116448650 | F13: 111230205 | G13: 4780000 | H13: =E13-F13-G13 -> 438445 | I13: =D13-F13 -> 148481847 | K13: =F13-G13 -> 106450205 | O13: 4400000
B14: 45627 | C14: 148481847 | D14: 221206702 | E14: =D14-C14 -> 72724855 | F14: 86954397 | G14: 4860000 | H14: =E14-F14-G14 -> -19089542 | I14: =D14-F14 -> 134252305 | K14: =F14-G14 -> 82094397 | O14: 4600000
B15: Total | D15: =SUM(D3:D14) -> 2337745457 | E15: =SUM(E3:E14) -> 1235666477 | F15: =SUM(F3:F14) -> 1100771672 | G15: =SUM(G3:G14) -> 56380000 | H15: =SUM(H3:H14) -> 78514805 | I15: =SUM(I3:I14) -> 1236973785
D19: Perhitungan HPP Toko
D20: Saldo Awal | F20: 86368576 | G20: Movement
D21: Pembelian | F21: =F15+G15 -> 1157151672
D22: Saldo Akhir | F22: =E35 -> 100178439
D23: HPP | F23: =F20+F21-F22 -> 1143341809
D25: Pendapatan Toko | F25: =E15-F21 -> 78514805 | G25: Laba
D26: Beban Toko | F26: =F15+G15 -> 1157151672
D27: Pembelian | F27: =F15 -> 1100771672
D28: Tfr ke Bendahara | F28: 0
D29: PER 31 DESEMBER 2024
D31: STOCK BARANG | E31: 1223986 | F31: confirmed
D32: CASH per 31 Dec 2024 | E32: 6720500 | F32: waiting confirmation
D33: Pulsa | E33: 768000 | F33: confirmed
D34: REKENING per 31 Dec 24 | E34: 91465953 | F34: confirmed
D35: Total Asset Toko | E35: =SUM(E31:E34) -> 100178439
D36: Modal balik ke bendahara | E36: 0
D37: Total Laba | E37: =E35-E36 -> 100178439
G38: =E35-F25 -> 21663634

Sheet Jurnal
H1: PEMASUKAN | K1: dulu pemasukan | M1: petty cash dari bank | N1: kas | O1: bank
H2: PENGELUARAN | K2: dulu pengeluaran | N2: bank | O2: kas
B4: 2025
B5: Tanggal | C5: Bank Code | D5: Keterangan | E5: Remarks | F5: Source | G5: No. Ref | H5: Debit | I5: Kredit
B6: 45658 | C6: 514 | D6: =IFERROR(VLOOKUP(C6,'Neraca Saldo'!$B$6:$C$56,2,0),"") -> Beban Lain-lain | E6: Write Off | F6: Bank | H6: 76113 | I6: 0
B7: 45658 | C7: 112 | D7: =IFERROR(VLOOKUP(C7,'Neraca Saldo'!$B$6:$C$56,2,0),"") -> Kas | E7: Write Off | F7: Bank | H7: 0 | I7: =H6 -> 76113
B8: 45659 | C8: 513 | D8: =IFERROR(VLOOKUP(C8,'Neraca Saldo'!$B$6:$C$56,2,0),"") -> Beban Pengurus dan Anggota | E8: Pelunasan Emaki - RAT Pengurus | F8: Bank | H8: 9924000 | I8: 0
B9: 45659 | C9: 111 | D9: =IFERROR(VLOOKUP(C9,'Neraca Saldo'!$B$6:$C$56,2,0),"") -> Bank | E9: Pelunasan Emaki - RAT Pengurus | F9: Bank | H9: 0 | I9: 9924000
B10: 45659 | C10: 513 | D10: =IFERROR(VLOOKUP(C10,'Neraca Saldo'!$B$6:$C$56,2,0),"") -> Beban Pengurus dan Anggota | E10: Pelunasan Karnevor - RAT Pengurus | F10: Bank | H10: 3152000 | I10: 0
B11: 45659 | C11: 111 | D11: =IFERROR(VLOOKUP(C11,'Neraca Saldo'!$B$6:$C$56,2,0),"") -> Bank | E11: Pelunasan Karnevor - RAT Pengurus | F11: Bank | H11: 0 | I11: 3152000
B12: 45659 | C12: 515 | D12: =IFERROR(VLOOKUP(C12,'Neraca Saldo'!$B$6:$C$56,2,0),"") -> Beban Gaji | E12: Pulsa Pengurus | F12: Petty Cash | H12: 700000 | I12: 0
B13: 45659 | C13: 112 | D13: =IFERROR(VLOOKUP(C13,'Neraca Saldo'!$B$6:$C$56,2,0),"") -> Kas | E13: Pulsa Pengurus | F13: Petty Cash | H13: 0 | I13: 700000
B14: 45659 | C14: 512 | D14: =IFERROR(VLOOKUP(C14,'Neraca Saldo'!$B$6:$C$56,2,0),"") -> Beban Jasa | E14: Perpanjangan webhosting | F14: Petty Cash | H14: 2712757 | I14: 0
B15: 45659 | C15: 112 | D15: =IFERROR(VLOOKUP(C15,'Neraca Saldo'!$B$6:$C$56,2,0),"") -> Kas | E15: Perpanjangan webhosting | F15: Petty Cash | H15: 0 | I15: 2712757
B16: 45659 | C16: 513 | D16: =IFERROR(VLOOKUP(C16,'Neraca Saldo'!$B$6:$C$56,2,0),"") -> Beban Pengurus dan Anggota | E16: Meals for Meeting | F16: Petty Cash | H16: 285300 | I16: 0
B17: 45659 | C17: 112 | D17: =IFERROR(VLOOKUP(C17,'Neraca Saldo'!$B$6:$C$56,2,0),"") -> Kas | E17: Meals for Meeting | F17: Petty Cash | H17: 0 | I17: 285300
B18: 45662 | C18: 111 | D18: =IFERROR(VLOOKUP(C18,'Neraca Saldo'!$B$6:$C$56,2,0),"") -> Bank | E18: NABUNG SUKARELA NOOR HIDAYAT | F18: Bank | H18: 800000 | I18: 0
B19: 45662 | C19: 212 | D19: =IFERROR(VLOOKUP(C19,'Neraca Saldo'!$B$6:$C$56,2,0),"") -> Simpanan Karyawan | E19: NABUNG SUKARELA NOOR HIDAYAT | F19: Bank | H19: 0 | I19: 800000
... B36: 45678 | C36: 513 | D36: =IFERROR(VLOOKUP(C36,'Neraca Saldo'!$B$6:$C$56,2,0),"") -> Beban Pengurus dan Anggota | E36: Meals for Meeting | F36: Petty Cash | H36: 45000 | I36: 0
B37: 45678 | C37: 112 | D37: =IFERROR(VLOOKUP(C37,'Neraca Saldo'!$B$6:$C$56,2,0),"") -> Kas | E37: Meals for Meeting | F37: Petty Cash | H37: =I36 -> 0 | I37: =H36 -> 45000
B38: 45679 | C38: 513 | D38: =IFERROR(VLOOKUP(C38,'Neraca Saldo'!$B$6:$C$56,2,0),"") -> Beban Pengurus dan Anggota | E38: Meals for Meeting | F38: Petty Cash | H38: 738000 | I38: 0
B39: 45679 | C39: 112 | D39: =IFERROR(VLOOKUP(C39,'Neraca Saldo'!$B$6:$C$56,2,0),"") -> Kas | E39: Meals for Meeting | F39: Petty Cash | H39: =I38 -> 0 | I39: =H38 -> 738000
B40: 45679 | C40: 513 | D40: =IFERROR(VLOOKUP(C40,'Neraca Saldo'!$B$6:$C$56,2,0),"") -> Beban Pengurus dan Anggota | E40: Meals for Meeting | F40: Petty Cash | H40: 235000 | I40: 0
B41: 45679 | C41: 112 | D41: =IFERROR(VLOOKUP(C41,'Neraca Saldo'!$B$6:$C$56,2,0),"") -> Kas | E41: Meals for Meeting | F41: Petty Cash | H41: =I40 -> 0 | I41: =H40 -> 235000
B42: 45679 | C42: 513 | D42: =IFERROR(VLOOKUP(C42,'Neraca Saldo'!$B$6:$C$56,2,0),"") -> Beban Pengurus dan Anggota | E42: Meals for Meeting | F42: Petty Cash | H42: 10000 | I42: 0
B43: 45679 | C43: 112 | D43: =IFERROR(VLOOKUP(C43,'Neraca Saldo'!$B$6:$C$56,2,0),"") -> Kas | E43: Meals for Meeting | F43: Petty Cash | H43: =I42 -> 0 | I43: =H42 -> 10000
B44: 45680 | C44: 111 | D44: =IFERROR(VLOOKUP(C44,'Neraca Saldo'!$B$6:$C$56,2,0),"") -> Bank | E44: INVOICE JAN 25 - Simpanan Wajib Anggota | F44: Bank | H44: 60000000 | I44: 0
B45: 45680 | C45: 212 | D45: =IFERROR(VLOOKUP(C45,'Neraca Saldo'!$B$6:$C$56,2,0),"") -> Simpanan Karyawan | E45: INVOICE JAN 25 - Simpanan Wajib Anggota | F45: Bank | H45: =I44 -> 0 | I45: =H44 -> 60000000
B46: 45680 | C46: 111 | D46: =IFERROR(VLOOKUP(C46,'Neraca Saldo'!$B$6:$C$56,2,0),"") -> Bank | E46: INVOICE JAN 25 - Simpanan Sukarela Berjangka | F46: Bank | H46: 27805500 | I46: 0
B47: 45680 | C47: 212 | D47: =IFERROR(VLOOKUP(C47,'Neraca Saldo'!$B$6:$C$56,2,0),"") -> Simpanan Karyawan | E47: INVOICE JAN 25 - Simpanan Sukarela Berjangka | F47: Bank | H47: =I46 -> 0 | I47: =H46 -> 27805500
B48: 45680 | C48: 111 | D48: =IFERROR(VLOOKUP(C48,'Neraca Saldo'!$B$6:$C$56,2,0),"") -> Bank | E48: INVOICE JAN 25 - Iuran Serikat Pekerja Nasional UTC | F48: Bank | H48: 5720000 | I48: 0
B49: 45680 | C49: 222 | D49: =IFERROR(VLOOKUP(C49,'Neraca Saldo'!$B$6:$C$56,2,0),"") -> Hutang SPN | E49: INVOICE JAN 25 - Iuran Serikat Pekerja Nasional UTC | F49: Bank | H49: =I48 -> 0 | I49: =H48 -> 5720000
B50: 45680 | C50: 111 | D50: =IFERROR(VLOOKUP(C50,'Neraca Saldo'!$B$6:$C$56,2,0),"") -> Bank | E50: INVOICE JAN 25 - Angsuran Pinjaman Barang | F50: Bank | H50: 59202965 | I50: 0
B51: 45680 | C51: 121 | D51: =IFERROR(VLOOKUP(C51,'Neraca Saldo'!$B$6:$C$56,2,0),"") -> Piutang Anggota | E51: INVOICE JAN 25 - Angsuran Pinjaman Barang | F51: Bank | H51: =I50 -> 0 | I51: =H50 -> 59202965
B52: 45680 | C52: 111 | D52: =IFERROR(VLOOKUP(C52,'Neraca Saldo'!$B$6:$C$56,2,0),"") -> Bank | E52: INVOICE JAN 25 - Angsuran Pinjaman Uang | F52: Bank | H52: 137285167 | I52: 0
B53: 45680 | C53: 121 | D53: =IFERROR(VLOOKUP(C53,'Neraca Saldo'!$B$6:$C$56,2,0),"") -> Piutang Anggota | E53: INVOICE JAN 25 - Angsuran Pinjaman Uang | F53: Bank | H53: =I52 -> 0 | I53: =H52 -> 137285167
B54: 45681 | C54: 411 | D54: =IFERROR(VLOOKUP(C54,'Neraca Saldo'!$B$6:$C$56,2,0),"") -> Pendapatan Toko | E54: Coklat Kaizen per Nov - Dec 2024 | F54: Bank | H54: 4646300 | I54: 0
B55: 45681 | C55: 111 | D55: =IFERROR(VLOOKUP(C55,'Neraca Saldo'!$B$6:$C$56,2,0),"") -> Bank | E55: Coklat Kaizen per Nov - Dec 2024 | F55: Bank | H55: =I54 -> 0 | I55: =H54 -> 4646300
B56: 45681 | C56: 124 | D56: =IFERROR(VLOOKUP(C56,'Neraca Saldo'!$B$6:$C$56,2,0),"") -> Piutang USP | E56: INVOICE JAN 25 - Simpanan Sukarela Berjangka | F56: Bank | H56: 27805500 | I56: 0
B57: 45681 | C57: 111 | D57: =IFERROR(VLOOKUP(C57,'Neraca Saldo'!$B$6:$C$56,2,0),"") -> Bank | E57: INVOICE JAN 25 - Simpanan Sukarela Berjangka | F57: Bank | H57: =I56 -> 0 | I57: =H56 -> 27805500
B58: 45681 | C58: 222 | D58: =IFERROR(VLOOKUP(C58,'Neraca Saldo'!$B$6:$C$56,2,0),"") -> Hutang SPN | E58: INVOICE JAN 25 - Iuran Serikat Pekerja Nasional UTC | F58: Bank | H58: 5720000 | I58: 0
B59: 45681 | C59: 111 | D59: =IFERROR(VLOOKUP(C59,'Neraca Saldo'!$B$6:$C$56,2,0),"") -> Bank | E59: INVOICE JAN 25 - Iuran Serikat Pekerja Nasional UTC | F59: Bank | H59: =I58 -> 0 | I59: =H58 -> 5720000
B60: 45681 | C60: 126 | D60: =IFERROR(VLOOKUP(C60,'Neraca Saldo'!$B$6:$C$56,2,0),"") -> Piutang Pengadaan | E60: INVOICE JAN 25 - Angsuran Pinjaman Barang | F60: Bank | H60: 59202965 | I60: 0
B61: 45681 | C61: 111 | D61: =IFERROR(VLOOKUP(C61,'Neraca Saldo'!$B$6:$C$56,2,0),"") -> Bank | E61: INVOICE JAN 25 - Angsuran Pinjaman Barang | F61: Bank | H61: =I60 -> 0 | I61: =H60 -> 59202965
B62: 45681 | C62: 124 | D62: =IFERROR(VLOOKUP(C62,'Neraca Saldo'!$B$6:$C$56,2,0),"") -> Piutang USP | E62: INVOICE JAN 25 - Angsuran Pinjaman Uang | F62: Bank | H62: 137285167 | I62: 0
B63: 45681 | C63: 111 | D63: =IFERROR(VLOOKUP(C63,'Neraca Saldo'!$B$6:$C$56,2,0),"") -> Bank | E63: INVOICE JAN 25 - Angsuran Pinjaman Uang | F63: Bank | H63: =I62 -> 0 | I63: =H62 -> 137285167
B64: 45681 | C64: 212 | D64: =IFERROR(VLOOKUP(C64,'Neraca Saldo'!$B$6:$C$56,2,0),"") -> Simpanan Karyawan | E64: Pencairan Tabungan Mochamad Izallihadi | F64: Bank | H64: 5850000 | I64: 0
B65: 45681 | C65: 111 | D65: =IFERROR(VLOOKUP(C65,'Neraca Saldo'!$B$6:$C$56,2,0),"") -> Bank | E65: Pencairan Tabungan Mochamad Izallihadi | F65: Bank | H65: 0 | I65: 5850000
B66: 45681 | C66: 212 | D66: =IFERROR(VLOOKUP(C66,'Neraca Saldo'!$B$6:$C$56,2,0),"") -> Simpanan Karyawan | E66: Pencairan Tabungan Agung Krisdiantoro | F66: Bank | H66: 1350000 | I66: 0
B67: 45681 | C67: 111 | D67: =IFERROR(VLOOKUP(C67,'Neraca Saldo'!$B$6:$C$56,2,0),"") -> Bank | E67: Pencairan Tabungan Agung Krisdiantoro | F67: Bank | H67: 0 | I67: 1350000
B68: 45681 | C68: 126 | D68: =IFERROR(VLOOKUP(C68,'Neraca Saldo'!$B$6:$C$56,2,0),"") -> Piutang Pengadaan | E68: TAMBAHAN MODAL PENGADAAN | F68: Bank | H68: 50000000 | I68: 0
B69: 45681 | C69: 111 | D69: =IFERROR(VLOOKUP(C69,'Neraca Saldo'!$B$6:$C$56,2,0),"") -> Bank | E69: TAMBAHAN MODAL PENGADAAN | F69: Bank | H69: 0 | I69: 50000000
B70: 45681 | C70: 112 | D70: =IFERROR(VLOOKUP(C70,'Neraca Saldo'!$B$6:$C$56,2,0),"") -> Kas | E70: Petty Cash | F70: Bank | H70: 998149 | I70: 0
B71: 45681 | C71: 111 | D71: =IFERROR(VLOOKUP(C71,'Neraca Saldo'!$B$6:$C$56,2,0),"") -> Bank | E71: Petty Cash | F71: Bank | H71: 0 | I71: 998149
B72: 45681 | C72: 111 | D72: =IFERROR(VLOOKUP(C72,'Neraca Saldo'!$B$6:$C$56,2,0),"") -> Bank | E72: Pengembalian Dana Emaki | F72: Bank | H72: 715500 | I72: 0
B73: 45681 | C73: 513 | D73: =IFERROR(VLOOKUP(C73,'Neraca Saldo'!$B$6:$C$56,2,0),"") -> Beban Pengurus dan Anggota | E73: Pengembalian Dana Emaki | F73: Bank | H73: 0 | I73: 715500
B74: 45682 | C74: 513 | D74: =IFERROR(VLOOKUP(C74,'Neraca Saldo'!$B$6:$C$56,2,0),"") -> Beban Pengurus dan Anggota | E74: Meals for Meeting (Emaki) | F74: Petty Cash | H74: 863800 | I74: 0
B75: 45682 | C75: 112 | D75: =IFERROR(VLOOKUP(C75,'Neraca Saldo'!$B$6:$C$56,2,0),"") -> Kas | E75: Meals for Meeting (Emaki) | F75: Petty Cash | H75: 0 | I75: 863800
B76: 45682 | C76: 513 | D76: =IFERROR(VLOOKUP(C76,'Neraca Saldo'!$B$6:$C$56,2,0),"") -> Beban Pengurus dan Anggota | E76: Meals for Meeting (Emaki) | F76: Petty Cash | H76: 341200 | I76: 0
B77: 45682 | C77: 112 | D77: =IFERROR(VLOOKUP(C77,'Neraca Saldo'!$B$6:$C$56,2,0),"") -> Kas | E77: Meals for Meeting (Emaki) | F77: Petty Cash | H77: 0 | I77: =H76 -> 341200
B78: 45682 | C78: 513 | D78: =IFERROR(VLOOKUP(C78,'Neraca Saldo'!$B$6:$C$56,2,0),"") -> Beban Pengurus dan Anggota | E78: Meals for Meeting (Emaki) | F78: Petty Cash | H78: 422200 | I78: 0
B79: 45682 | C79: 112 | D79: =IFERROR(VLOOKUP(C79,'Neraca Saldo'!$B$6:$C$56,2,0),"") -> Kas | E79: Meals for Meeting (Emaki) | F79: Petty Cash | H79: 0 | I79: =H78 -> 422200
B80: 45682 | C80: 513 | D80: =IFERROR(VLOOKUP(C80,'Neraca Saldo'!$B$6:$C$56,2,0),"") -> Beban Pengurus dan Anggota | E80: Meals for Meeting (Emaki) | F80: Petty Cash | H80: 467900 | I80: 0
B81: 45682 | C81: 112 | D81: =IFERROR(VLOOKUP(C81,'Neraca Saldo'!$B$6:$C$56,2,0),"") -> Kas | E81: Meals for Meeting (Emaki) | F81: Petty Cash | H81: 0 | I81: =H80 -> 467900
B82: 45682 | C82: 513 | D82: =IFERROR(VLOOKUP(C82,'Neraca Saldo'!$B$6:$C$56,2,0),"") -> Beban Pengurus dan Anggota | E82: Transport and Meals (Emaki) | F82: Petty Cash | H82: 5125000 | I82: 0
B83: 45682 | C83: 112 | D83: =IFERROR(VLOOKUP(C83,'Neraca Saldo'!$B$6:$C$56,2,0),"") -> Kas | E83: Transport and Meals (Emaki) | F83: Petty Cash | H83: 0 | I83: =H82 -> 5125000
B84: 45682 | C84: 513 | D84: =IFERROR(VLOOKUP(C84,'Neraca Saldo'!$B$6:$C$56,2,0),"") -> Beban Pengurus dan Anggota | E84: Additional Rice for Dinner (Emaki) | F84: Petty Cash | H84: 204000 | I84: 0
B85: 45682 | C85: 112 | D85: =IFERROR(VLOOKUP(C85,'Neraca Saldo'!$B$6:$C$56,2,0),"") -> Kas | E85: Additional Rice for Dinner (Emaki) | F85: Petty Cash | H85: 0 | I85: =H84 -> 204000
B86: 45682 | C86: 513 | D86: =IFERROR(VLOOKUP(C86,'Neraca Saldo'!$B$6:$C$56,2,0),"") -> Beban Pengurus dan Anggota | E86: Additional Bfast (Emaki) | F86: Petty Cash | H86: 200000 | I86: 0
B87: 45682 | C87: 112 | D87: =IFERROR(VLOOKUP(C87,'Neraca Saldo'!$B$6:$C$56,2,0),"") -> Kas | E87: Additional Bfast (Emaki) | F87: Petty Cash | H87: 0 | I87: 200000
B88: 45683 | C88: 112 | D88: =IFERROR(VLOOKUP(C88,'Neraca Saldo'!$B$6:$C$56,2,0),"") -> Kas | E88: Deposit return from Karnivor (Emaki) | F88: Petty Cash | H88: 550000 | I88: 0
B89: 45683 | C89: 513 | D89: =IFERROR(VLOOKUP(C89,'Neraca Saldo'!$B$6:$C$56,2,0),"") -> Beban Pengurus dan Anggota | E89: Deposit return from Karnivor (Emaki) | F89: Petty Cash | H89: 0 | I89: 550000
B90: 45685 | C90: 112 | D90: =IFERROR(VLOOKUP(C90,'Neraca Saldo'!$B$6:$C$56,2,0),"") -> Kas | E90: Petty Cash | F90: Bank | H90: 13000000 | I90: 0
B91: 45685 | C91: 111 | D91: =IFERROR(VLOOKUP(C91,'Neraca Saldo'!$B$6:$C$56,2,0),"") -> Bank | E91: Petty Cash | F91: Bank | H91: 0 | I91: 13000000
B92: 45685 | C92: 523 | D92: =IFERROR(VLOOKUP(C92,'Neraca Saldo'!$B$6:$C$56,2,0),"") -> Beban RAT | E92: DP Pawon Pitoe (RAT) | F92: Petty Cash | H92: 3000000 | I92: 0
B93: 45685 | C93: 112 | D93: =IFERROR(VLOOKUP(C93,'Neraca Saldo'!$B$6:$C$56,2,0),"") -> Kas | E93: DP Pawon Pitoe (RAT) | F93: Petty Cash | H93: 0 | I93: 3000000
B94: 45686 | C94: 520 | D94: =IFERROR(VLOOKUP(C94,'Neraca Saldo'!$B$6:$C$56,2,0),"") -> Beban Perlengkapan | E94: Pembelian Etalase Toko | F94: Petty Cash | H94: 250000 | I94: 0
B95: 45686 | C95: 112 | D95: =IFERROR(VLOOKUP(C95,'Neraca Saldo'!$B$6:$C$56,2,0),"") -> Kas | E95: Pembelian Etalase Toko | F95: Petty Cash | H95: 0 | I95: =H94 -> 250000
B96: 45686 | C96: 513 | D96: =IFERROR(VLOOKUP(C96,'Neraca Saldo'!$B$6:$C$56,2,0),"") -> Beban Pengurus dan Anggota | E96: Meals for exchanging rug | F96: Petty Cash | H96: 608302 | I96: 0
B97: 45686 | C97: 112 | D97: =IFERROR(VLOOKUP(C97,'Neraca Saldo'!$B$6:$C$56,2,0),"") -> Kas | E97: Meals for exchanging rug | F97: Petty Cash | H97: 0 | I97: 608302
B98: 45687 | C98: 523 | D98: =IFERROR(VLOOKUP(C98,'Neraca Saldo'!$B$6:$C$56,2,0),"") -> Beban RAT | E98: Pembelian Doorprize RAT - Via Cw | F98: Petty Cash | H98: 4734145 | I98: 0
B99: 45687 | C99: 112 | D99: =IFERROR(VLOOKUP(C99,'Neraca Saldo'!$B$6:$C$56,2,0),"") -> Kas | E99: Pembelian Doorprize RAT - Via Cw | F99: Petty Cash | H99: 0 | I99: 4734145
B100: 45687 | C100: 523 | D100: =IFERROR(VLOOKUP(C100,'Neraca Saldo'!$B$6:$C$56,2,0),"") -> Beban RAT | E100: Pembelian Doorprize RAT - Via Dian | F100: Petty Cash | H100: 4281922 | I100: 0
B101: 45687 | C101: 112 | D101: =IFERROR(VLOOKUP(C101,'Neraca Saldo'!$B$6:$C$56,2,0),"") -> Kas | E101: Pembelian Doorprize RAT - Via Dian | F101: Petty Cash | H101: 0 | I101: 4281922
B102: 45687 | C102: 523 | D102: =IFERROR(VLOOKUP(C102,'Neraca Saldo'!$B$6:$C$56,2,0),"") -> Beban RAT | E102: Pembelian Doorprize RAT - Via Ayu | F102: Petty Cash | H102: 959500 | I102: 0
B103: 45687 | C103: 112 | D103: =IFERROR(VLOOKUP(C103,'Neraca Saldo'!$B$6:$C$56,2,0),"") -> Kas | E103: Pembelian Doorprize RAT - Via Ayu | F103: Petty Cash | H103: 0 | I103: 959500
B104: 45688 | C104: 111 | D104: =IFERROR(VLOOKUP(C104,'Neraca Saldo'!$B$6:$C$56,2,0),"") -> Bank | E104: Bunga | F104: Bank | H104: 17479 | I104: 0
B105: 45688 | C105: 413 | D105: =IFERROR(VLOOKUP(C105,'Neraca Saldo'!$B$6:$C$56,2,0),"") -> Pendapatan Jasa Bank | E105: Bunga | F105: Bank | H105: 0 | I105: 17479
B106: 45688 | C106: 521 | D106: =IFERROR(VLOOKUP(C106,'Neraca Saldo'!$B$6:$C$56,2,0),"") -> Beban Biaya Bank | E106: PPH | F106: Bank | H106: 3496 | I106: 0
B107: 45688 | C107: 111 | D107: =IFERROR(VLOOKUP(C107,'Neraca Saldo'!$B$6:$C$56,2,0),"") -> Bank | E107: PPH | F107: Bank | H107: 0 | I107: 3496
... B145: 45701 | C145: 111 | D145: =IFERROR(VLOOKUP(C145,'Neraca Saldo'!$B$6:$C$56,2,0),"") -> Bank | E145: Petty Cash | F145: Bank | H145: 0 | I145: 7167305
B146: 45701 | C146: 523 | D146: =IFERROR(VLOOKUP(C146,'Neraca Saldo'!$B$6:$C$56,2,0),"") -> Beban RAT | E146: Pembelian Amplop RAT | F146: Petty Cash | H146: =119512+57000 -> 176512 | I146: 0
B147: 45701 | C147: 112 | D147: =IFERROR(VLOOKUP(C147,'Neraca Saldo'!$B$6:$C$56,2,0),"") -> Kas | E147: Pembelian Amplop RAT | F147: Petty Cash | H147: 0 | I147: =119512+57000 -> 176512
B148: 45701 | C148: 523 | D148: =IFERROR(VLOOKUP(C148,'Neraca Saldo'!$B$6:$C$56,2,0),"") -> Beban RAT | E148: Pelunasan Pawon Pitoe - RAT | F148: Petty Cash | H148: 3000000 | I148: 0
B149: 45701 | C149: 112 | D149: =IFERROR(VLOOKUP(C149,'Neraca Saldo'!$B$6:$C$56,2,0),"") -> Kas | E149: Pelunasan Pawon Pitoe - RAT | F149: Petty Cash | H149: 0 | I149: 3000000
B150: 45701 | C150: 517 | D150: =IFERROR(VLOOKUP(C150,'Neraca Saldo'!$B$6:$C$56,2,0),"") -> Beban Transport | E150: Lumpsump for Cw to Pawon Pitoe | F150: Petty Cash | H150: 200000 | I150: 0
B151: 45701 | C151: 112 | D151: =IFERROR(VLOOKUP(C151,'Neraca Saldo'!$B$6:$C$56,2,0),"") -> Kas | E151: Lumpsump for Cw to Pawon Pitoe | F151: Petty Cash | H151: 0 | I151: 200000
B152: 45701 | C152: 523 | D152: =IFERROR(VLOOKUP(C152,'Neraca Saldo'!$B$6:$C$56,2,0),"") -> Beban RAT | E152: Transport Pengambilan Baju RAT | F152: Petty Cash | H152: 21000 | I152: 0
B153: 45701 | C153: 112 | D153: =IFERROR(VLOOKUP(C153,'Neraca Saldo'!$B$6:$C$56,2,0),"") -> Kas | E153: Transport Pengambilan Baju RAT | F153: Petty Cash | H153: 0 | I153: 21000
B154: 45702 | C154: 523 | D154: =IFERROR(VLOOKUP(C154,'Neraca Saldo'!$B$6:$C$56,2,0),"") -> Beban RAT | E154: Meals for meeting (RAT preparation) | F154: Petty Cash | H154: 282800 | I154: 0
...

Sheet Neraca Saldo
B1: KOPERASI KARYAWAN
B2: AEROSPACE
B3: N E R A C A S A L D O | I3: 17044310
B4: per 31 Desember 2025 | I4: =I3-G8 -> -0.84848404
B5: 2025
B6: Kode Akun | C6: Keterangan | D6: Saldo Awal | E6: Debit | F6: Kredit | G6: Saldo Akhir | H6: D/K | L6: as Per Data | N6: Recon | Q6: Modal USP | U6: Berjangka
B7: 1 | C7: Harta | K7: Uang ditangan | L7: =G15 -> 65170235 | N7: Modal USP | O7: =940000000+400000000+156353000 -> 1496353000 | Q7: 2019 | R7: 190000000 | T7: Didapat | U7: Dikembalikan
A8: Kas & Bank | B8: 111 | C8: Bank | D8: 40474149 | E8: =SUMIF(Jurnal!$C$6:$C$1648,'Neraca Saldo'!$B$7:$B$55,Jurnal!$H$6:$H$1648) -> 4617966491 | F8: =SUMIF(Jurnal!$C$6:$C$1648,'Neraca Saldo'!$B$7:$B$55,Jurnal!$I$6:$I$1648) -> 4641396329 | G8: =D8+E8-F8 -> 17044311 | H8: D | I8: saldo akhir pindah ke saldo awal | K8: AR USP | L8: 1.0924679e+09 | N8: Jasa 2025 | O8: =G39+G37 -> 362320150 | Q8: 2020 | R8: 219000000
A9: Kas & Bank | B9: 112 | C9: Kas | D9: 5243082 | E9: =SUMIF(Jurnal!$C$6:$C$1648,'Neraca Saldo'!$B$7:$B$55,Jurnal!$H$6:$H$1648) -> 324159552 | F9: =SUMIF(Jurnal!$C$6:$C$1648,'Neraca Saldo'!$B$7:$B$55,Jurnal!$I$6:$I$1648) -> 315778294 | G9: =D9+E9-F9 -> 13624340 | H9: D | I9: 13124340 | J9: =G9-I9 -> 500000 | K9: AR Pengadaan | L9: =#REF! -> #REF! | N9: Porsi Pengadaan | Q9: 2021 | R9: 190000000
A10: Piutang Anggota | B10: 121 | C10: Piutang Anggota | D10: 2.8335992e+09 | E10: =SUMIF(Jurnal!$C$6:$C$1648,'Neraca Saldo'!$B$7:$B$55,Jurnal!$H$6:$H$1648) -> 3841096361 | F10: =SUMIF(Jurnal!$C$6:$C$1648,'Neraca Saldo'!$B$7:$B$55,Jurnal!$I$6:$I$1648) -> 3661363012 | G10: =D10+E10-F10 -> 3.0133326e+09 | H10: D | L10: =SUM(L7:L9) -> #REF! | N10: Jasa Pengadaan | Q10: 2022 | R10: 111000000
A11: Piutang Jasa | B11: 122 | C11: Piutang Jasa | D11: 0 | E11: =SUMIF(Jurnal!$C$6:$C$1648,'Neraca Saldo'!$B$7:$B$55,Jurnal!$H$6:$H$1648) -> 0 | F11: =SUMIF(Jurnal!$C$6:$C$1648,'Neraca Saldo'!$B$7:$B$55,Jurnal!$I$6:$I$1648) -> 0 | G11: =D11+E11-F11 -> 0 | H11: D | L11: =L10-(G10+G13+G15) -> #REF! | N11: Saldo AR seharusnya | O11: =SUM(O7:O10) -> 1858673150 | Q11: 2023 | R11: 230000000
A12: Piutang Unit Toko | B12: 123 | C12: Piutang Toko | D12: 104738319 | E12: =SUMIF(Jurnal!$C$6:$C$1648,'Neraca Saldo'!$B$7:$B$55,Jurnal!$H$6:$H$1648) -> 1227746947 | F12: =SUMIF(Jurnal!$C$6:$C$1648,'Neraca Saldo'!$B$7:$B$55,Jurnal!$I$6:$I$1648) -> 1.1897405e+09 | G12: =D12+E12-F12 -> 1.4274476e+08 | H12: D | I12: 145163465 | J12: =G12-I12 -> -2418709.7 | N12: Saldo LK | O12: =G10+G13+G15 -> 3.322853e+09
A13: Piutang Unit Simpan Pinjam | B13: 124 | C13: Piutang USP | D13: -397152390 | E13: =SUMIF(Jurnal!$C$6:$C$1648,'Neraca Saldo'!$B$7:$B$55,Jurnal!$H$6:$H$1648) -> 2931502578 | F13: =SUMIF(Jurnal!$C$6:$C$1648,'Neraca Saldo'!$B$7:$B$55,Jurnal!$I$6:$I$1648) -> 2290000000 | G13: =D13+E13-F13 -> 244350188 | H13: D | I13: 235600188 | N13: Selisih | O13: =O11-O12 -> -1.4641798e+09 | Q13: Sukarela
A14: Piutang Collins | B14: 125 | C14: Piutang Collins | D14: 0 | E14: =SUMIF(Jurnal!$C$6:$C$1648,'Neraca Saldo'!$B$7:$B$55,Jurnal!$H$6:$H$1648) -> 0 | F14: =SUMIF(Jurnal!$C$6:$C$1648,'Neraca Saldo'!$B$7:$B$55,Jurnal!$I$6:$I$1648) -> 0 | G14: =D14+E14-F14 -> 0 | H14: D | I14: =G13-I13 -> 8750000 | J14: 155010422 | K14: =I14-J14 -> -146260422 | L14: 4812000 | M14: =K14-L14 -> -151072422 | R14: =SUM(R7:R13) -> 940000000
A15: Piutang Pengadaan | B15: 126 | C15: Piutang Pengadaan | D15: 1249550.2 | E15: =SUMIF(Jurnal!$C$6:$C$1648,'Neraca Saldo'!$B$7:$B$55,Jurnal!$H$6:$H$1648) -> 1329184375 | F15: =SUMIF(Jurnal!$C$6:$C$1648,'Neraca Saldo'!$B$7:$B$55,Jurnal!$I$6:$I$1648) -> 1265263690 | G15: =D15+E15-F15 -> 65170235 | H15: D | I15: 65170235 | J15: =I15-G15 -> -0.20707083 | R15: =O8/R14 -> 0.38544697
A16: Nilai Perolehan | B16: 131 | C16: Nilai Perolehan | D16: 0 | E16: =SUMIF(Jurnal!$C$6:$C$1648,'Neraca Saldo'!$B$7:$B$55,Jurnal!$H$6:$H$1648) -> 0 | F16: =SUMIF(Jurnal!$C$6:$C$1648,'Neraca Saldo'!$B$7:$B$55,Jurnal!$I$6:$I$1648) -> 0 | G16: =D16+E16-F16 -> 0 | H16: D | K16: Selisih Saldo Bank | L16: =G8-[2]BANK!$G$915 -> -43243113 | M16: Saldo Mandiri (closed) | R16: =R14+G37 -> 1153716844
A17: Akumulasi Penyusutan | B17: 132 | C17: Akumulasi Penyusutan | D17: 0 | E17: =SUMIF(Jurnal!$C$6:$C$1648,'Neraca Saldo'!$B$7:$B$55,Jurnal!$H$6:$H$1648) -> 0 | F17: =SUMIF(Jurnal!$C$6:$C$1648,'Neraca Saldo'!$B$7:$B$55,Jurnal!$I$6:$I$1648) -> 0 | G17: =D17+E17-F17 -> 0 | H17: K | K17: Selisih Saldo Kas | L17: =G9-[2]Kas!$G$262 -> -6019573
A18: Persediaan Barang Dagangan | B18: 141 | C18: Inventory | D18: 1223986 | E18: =SUMIF(Jurnal!$C$6:$C$1648,'Neraca Saldo'!$B$7:$B$55,Jurnal!$H$6:$H$1648) -> 18343491 | F18: =SUMIF(Jurnal!$C$6:$C$1648,'Neraca Saldo'!$B$7:$B$55,Jurnal!$I$6:$I$1648) -> 0 | G18: =D18+E18-F18 -> 19567477 | H18: D | K18: Selisih Saldo Pengadaan | L18: =G15-#REF! -> #REF! | R18: 1395000000 | S18: Modal
E19: =SUMIF(Jurnal!$C$6:$C$1648,'Neraca Saldo'!$B$7:$B$55,Jurnal!$H$6:$H$1648) -> 0 | F19: =SUMIF(Jurnal!$C$6:$C$1648,'Neraca Saldo'!$B$7:$B$55,Jurnal!$I$6:$I$1648) -> 0 | N19: Pengadaan | O19: 1.2331416e+09 | R19: 300509500 | S19: Berjangka
E20: =SUMIF(Jurnal!$C$6:$C$1648,'Neraca Saldo'!$B$7:$B$55,Jurnal!$H$6:$H$1648) -> 0 | F20: =SUMIF(Jurnal!$C$6:$C$1648,'Neraca Saldo'!$B$7:$B$55,Jurnal!$I$6:$I$1648) -> 0 | N20: USP | O20: 1.6698181e+09 | R20: 213000000
B21: 211 | C21: Utang | D21: 0 | E21: =SUMIF(Jurnal!$C$6:$C$1648,'Neraca Saldo'!$B$7:$B$55,Jurnal!$H$6:$H$1648) -> 0 | F21: =SUMIF(Jurnal!$C$6:$C$1648,'Neraca Saldo'!$B$7:$B$55,Jurnal!$I$6:$I$1648) -> 0 | G21: =D21+E21-F21 -> 0 | H21: K | K21: LK | L21: =G22 -> -3294007563 | O21: =O19+O20+O18 -> 2.9029597e+09 | R21: =SUM(R18:R20) -> 1908509500
A22: Simpanan Karyawan | B22: 212 | C22: Simpanan Karyawan | D22: -2403930500 | E22: =SUMIF(Jurnal!$C$6:$C$1648,'Neraca Saldo'!$B$7:$B$55,Jurnal!$H$6:$H$1648) -> 414031000 | F22: =SUMIF(Jurnal!$C$6:$C$1648,'Neraca Saldo'!$B$7:$B$55,Jurnal!$I$6:$I$1648) -> 1304108063 | G22: =D22+E22-F22 -> -3294007563 | H22: K | K22: Tabel Simpanan | L22: =2857400000+36650000+9117000+100000000+300509500 -> 3303676500 | M22: Reconcil Tabel | N22: Neraca | O22: =+G10 -> 3.0133326e+09
A23: Hutang Lain-lain | B23: 213 | C23: Hutang Lain-lain | D23: 0 | E23: =SUMIF(Jurnal!$C$6:$C$1648,'Neraca Saldo'!$B$7:$B$55,Jurnal!$H$6:$H$1648) -> 250000 | F23: =SUMIF(Jurnal!$C$6:$C$1648,'Neraca Saldo'!$B$7:$B$55,Jurnal!$I$6:$I$1648) -> 250000 | G23: =D23+E23-F23 -> 0 | H23: K | K23: 0 | L23: =L22+L21 -> 9668937 | M23: >>> Selisih sukarela | O23: =O22-O21 -> 1.103729e+08
A24: Dana Sosial | B24: 221 | C24: Dana Sosial | D24: 0 | E24: =SUMIF(Jurnal!$C$6:$C$1648,'Neraca Saldo'!$B$7:$B$55,Jurnal!$H$6:$H$1648) -> 0 | F24: =SUMIF(Jurnal!$C$6:$C$1648,'Neraca Saldo'!$B$7:$B$55,Jurnal!$I$6:$I$1648) -> 0 | G24: =D24+E24-F24 -> 0 | H24: K | L24: =K23-L23 -> -9668937 | O24: 48496953
A25: Hutang SPN | B25: 222 | C25: Hutang SPN | D25: 0 | E25: =SUMIF(Jurnal!$C$6:$C$1648,'Neraca Saldo'!$B$7:$B$55,Jurnal!$H$6:$H$1648) -> 80765000 | F25: =SUMIF(Jurnal!$C$6:$C$1648,'Neraca Saldo'!$B$7:$B$55,Jurnal!$I$6:$I$1648) -> 80765000 | G25: =D25+E25-F25 -> 0 | H25: K | O25: =O23-O24 -> 61875945
A26: Hutang SHU | B26: 231 | C26: Hutang SHU | D26: 0 | E26: =SUMIF(Jurnal!$C$6:$C$1648,'Neraca Saldo'!$B$7:$B$55,Jurnal!$H$6:$H$1648) -> 0 | F26: =SUMIF(Jurnal!$C$6:$C$1648,'Neraca Saldo'!$B$7:$B$55,Jurnal!$I$6:$I$1648) -> 0 | G26: =D26+E26-F26 -> 0 | H26: K
A27: Hutang Pajak | B27: 232 | C27: Hutang Pajak | D27: -7266978.2 | E27: =SUMIF(Jurnal!$C$6:$C$1648,'Neraca Saldo'!$B$7:$B$55,Jurnal!$H$6:$H$1648) -> 7267978 | F27: =SUMIF(Jurnal!$C$6:$C$1648,'Neraca Saldo'!$B$7:$B$55,Jurnal!$I$6:$I$1648) -> 23598627 | G27: =D27+E27-F27 -> -23597627 | H27: K
E28: =SUMIF(Jurnal!$C$6:$C$1648,'Neraca Saldo'!$B$7:$B$55,Jurnal!$H$6:$H$1648) -> 0 | F28: =SUMIF(Jurnal!$C$6:$C$1648,'Neraca Saldo'!$B$7:$B$55,Jurnal!$I$6:$I$1648) -> 0
B29: 311 | C29: Modal | E29: =SUMIF(Jurnal!$C$6:$C$1648,'Neraca Saldo'!$B$7:$B$55,Jurnal!$H$6:$H$1648) -> 0 | F29: =SUMIF(Jurnal!$C$6:$C$1648,'Neraca Saldo'!$B$7:$B$55,Jurnal!$I$6:$I$1648) -> 0
A30: Modal Awal | B30: 312 | C30: Modal Awal | D30: 0 | E30: =SUMIF(Jurnal!$C$6:$C$1648,'Neraca Saldo'!$B$7:$B$55,Jurnal!$H$6:$H$1648) -> 0 | F30: =SUMIF(Jurnal!$C$6:$C$1648,'Neraca Saldo'!$B$7:$B$55,Jurnal!$I$6:$I$1648) -> 0 | G30: =D30+E30-F30 -> 0 | H30: K | I30: -7294332.7 | K30: Toko :
A31: (Laba)/Rugi ditahan | B31: 313 | C31: (Laba)/Rugi ditahan | D31: =-100975599.087121+93926000-171128833.61 -> -1.7817843e+08 | E31: =SUMIF(Jurnal!$C$6:$C$1648,'Neraca Saldo'!$B$7:$B$55,Jurnal!$H$6:$H$1648) -> 99385100 | F31: =SUMIF(Jurnal!$C$6:$C$1648,'Neraca Saldo'!$B$7:$B$55,Jurnal!$I$6:$I$1648) -> 40000000 | G31: =D31+E31-F31 -> -1.1879333e+08 | H31: K | I31: =G31+G32 -> -7294332.7 | K31: Barang | L31: =G18 -> 19567477
A32: SHU yang dibagikan | B32: 314 | C32: SHU yang dibagikan | D32: 0 | E32: =SUMIF(Jurnal!$C$6:$C$1648,'Neraca Saldo'!$B$7:$B$55,Jurnal!$H$6:$H$1648) -> 111499000 | F32: =SUMIF(Jurnal!$C$6:$C$1648,'Neraca Saldo'!$B$7:$B$55,Jurnal!$I$6:$I$1648) -> 0 | G32: =D32+E32-F32 -> 111499000 | H32: K | K32: Uang Modal | L32: =25000000-L31 -> 5432523
A33: Laba/(Rugi) Periode Berjalan | B33: 315 | C33: (Laba)/Rugi Periode Berjalan | D33: 0 | E33: =SUMIF(Jurnal!$C$6:$C$1648,'Neraca Saldo'!$B$7:$B$55,Jurnal!$H$6:$H$1648) -> 0 | F33: =SUM(G36:G40)-SUM(G42:G54) -> 1.9093435e+08 | G33: =D33+E33-F33 -> -1.9093435e+08 | H33: K | K33: Uang Laba | L33: =G36-G42 -> 1.5351723e+08
E34: =SUMIF(Jurnal!$C$6:$C$1648,'Neraca Saldo'!$B$7:$B$55,Jurnal!$H$6:$H$1648) -> 0 | F34: =SUMIF(Jurnal!$C$8:$C$1648,'Neraca Saldo'!$B$7:$B$55,Jurnal!$I$8:$I$1648) -> 0 | L34: =SUM(L31:L33) -> 1.7851723e+08
B35: 4 | C35: Pendapatan | E35: =SUMIF(Jurnal!$C$6:$C$1648,'Neraca Saldo'!$B$7:$B$55,Jurnal!$H$6:$H$1648) -> 0 | F35: =SUMIF(Jurnal!$C$6:$C$1648,'Neraca Saldo'!$B$7:$B$55,Jurnal!$I$6:$I$1648) -> 0
A36: Pendapatan Toko | B36: 411 | C36: Pendapatan Toko | E36: =SUMIF(Jurnal!$C$6:$C$1648,'Neraca Saldo'!$B$7:$B$55,Jurnal!$H$6:$H$1648) -> 92107350 | F36: =SUMIF(Jurnal!$C$6:$C$1648,'Neraca Saldo'!$B$7:$B$55,Jurnal!$I$6:$I$1648) -> 1319854297 | G36: =+F36-E36 -> 1227746947 | H36: K
A37: Pendapatan Jasa Pinjaman | B37: 412 | C37: Pendapatan Jasa Pinjaman | E37: =SUMIF(Jurnal!$C$6:$C$1648,'Neraca Saldo'!$B$7:$B$55,Jurnal!$H$6:$H$1648) -> 0 | F37: =SUMIF(Jurnal!$C$6:$C$1648,'Neraca Saldo'!$B$7:$B$55,Jurnal!$I$6:$I$1648) -> 213716844 | G37: =+F37-E37 -> 213716844 | H37: K
A38: Pendapatan Lain-lain | B38: 413 | C38: Pendapatan Jasa Bank | E38: =SUMIF(Jurnal!$C$6:$C$1648,'Neraca Saldo'!$B$7:$B$55,Jurnal!$H$6:$H$1648) -> 0 | F38: =SUMIF(Jurnal!$C$6:$C$1648,'Neraca Saldo'!$B$7:$B$55,Jurnal!$I$6:$I$1648) -> 335890 | G38: =+F38-E38 -> 335890 | H38: K
A39: Pendapatan Jasa Pengadaan | B39: 414 | C39: Pendapatan Jasa Pengadaan | E39: =SUMIF(Jurnal!$C$6:$C$1648,'Neraca Saldo'!$B$7:$B$55,Jurnal!$H$6:$H$1648) -> 0 | F39: =SUMIF(Jurnal!$C$6:$C$1648,'Neraca Saldo'!$B$7:$B$55,Jurnal!$I$6:$I$1648) -> 148603306 | G39: =+F39-E39 -> 148603306 | H39: K
A40: Pendapatan Lain-lain | B40: 415 | C40: Pendapatan Lain-lain | E40: =SUMIF(Jurnal!$C$6:$C$1648,'Neraca Saldo'!$B$7:$B$55,Jurnal!$H$6:$H$1648) -> 0 | F40: =SUMIF(Jurnal!$C$6:$C$1648,'Neraca Saldo'!$B$7:$B$55,Jurnal!$I$6:$I$1648) -> 1408000 | G40: =+F40-E40 -> 1408000 | H40: K
E41: =SUMIF(Jurnal!$C$6:$C$1648,'Neraca Saldo'!$B$7:$B$55,Jurnal!$H$6:$H$1648) -> 0 | F41: =SUMIF(Jurnal!$C$6:$C$1648,'Neraca Saldo'!$B$7:$B$55,Jurnal!$I$6:$I$1648) -> 0
A42: Harga Pokok Penjualan | B42: 511 | C42: Beban Pokok Penjualan | E42: =SUMIF(Jurnal!$C$6:$C$1648,'Neraca Saldo'!$B$7:$B$55,Jurnal!$H$6:$H$1648) -> 1.0742297e+09 | F42: =SUMIF(Jurnal!$C$6:$C$1648,'Neraca Saldo'!$B$7:$B$55,Jurnal!$I$6:$I$1648) -> 0 | G42: =+E42-F42 -> 1.0742297e+09 | I42: 1129618672 | K42: =+I42-G42 -> 55388957
A43: Beban Jasa | B43: 512 | C43: Beban Jasa | E43: =SUMIF(Jurnal!$C$6:$C$1648,'Neraca Saldo'!$B$7:$B$55,Jurnal!$H$6:$H$1648) -> 5529757 | F43: =SUMIF(Jurnal!$C$6:$C$1648,'Neraca Saldo'!$B$7:$B$55,Jurnal!$I$6:$I$1648) -> 0 | G43: =+E43-F43 -> 5529757 | H43: D | I43: 7850000 | K43: =+I43-G43 -> 2320243
A44: Beban Pengurus dan Anggota | B44: 513 | C44: Beban Pengurus dan Anggota | E44: =SUMIF(Jurnal!$C$6:$C$1648,'Neraca Saldo'!$B$7:$B$55,Jurnal!$H$6:$H$1648) -> 106787832 | F44: =SUMIF(Jurnal!$C$6:$C$1648,'Neraca Saldo'!$B$7:$B$55,Jurnal!$I$6:$I$1648) -> 1755500 | G44: =+E44-F44 -> 105032332 | H44: D | I44: 63399690 | K44: =+I44-G44 -> -41632642
A45: Beban Lain-lain | B45: 514 | C45: Beban Lain-lain | E45: =SUMIF(Jurnal!$C$6:$C$1648,'Neraca Saldo'!$B$7:$B$55,Jurnal!$H$6:$H$1648) -> 76113 | F45: =SUMIF(Jurnal!$C$6:$C$1648,'Neraca Saldo'!$B$7:$B$55,Jurnal!$I$6:$I$1648) -> 0 | G45: =+E45-F45 -> 76113 | H45: D | I45: 0 | K45: =+I45-G45 -> -76113
A46: Beban Gaji | B46: 515 | C46: Beban Gaji | E46: =SUMIF(Jurnal!$C$6:$C$1648,'Neraca Saldo'!$B$7:$B$55,Jurnal!$H$6:$H$1648) -> 126860000 | F46: =SUMIF(Jurnal!$C$6:$C$1648,'Neraca Saldo'!$B$7:$B$55,Jurnal!$I$6:$I$1648) -> 0 | G46: =+E46-F46 -> 126860000 | H46: D | I46: 46300000 | K46: =+I46-G46 -> -80560000
A47: Beban ATK | B47: 516 | C47: Beban ATK | E47: =SUMIF(Jurnal!$C$6:$C$1648,'Neraca Saldo'!$B$7:$B$55,Jurnal!$H$6:$H$1648) -> 3142573 | F47: =SUMIF(Jurnal!$C$6:$C$1648,'Neraca Saldo'!$B$7:$B$55,Jurnal!$I$6:$I$1648) -> 0 | G47: =+E47-F47 -> 3142573 | H47: D | I47: 2471402 | K47: =+I47-G47 -> -671171
A48: Beban Transport | B48: 517 | C48: Beban Transport | E48: =SUMIF(Jurnal!$C$6:$C$1648,'Neraca Saldo'!$B$7:$B$55,Jurnal!$H$6:$H$1648) -> 6090000 | F48: =SUMIF(Jurnal!$C$6:$C$1648,'Neraca Saldo'!$B$7:$B$55,Jurnal!$I$6:$I$1648) -> 0 | G48: =+E48-F48 -> 6090000 | H48: D | I48: 3501546 | K48: =+I48-G48 -> -2588454
A49: Beban Training | B49: 518 | C49: Beban Training | E49: =SUMIF(Jurnal!$C$6:$C$1648,'Neraca Saldo'!$B$7:$B$55,Jurnal!$H$6:$H$1648) -> 6387409 | F49: =SUMIF(Jurnal!$C$6:$C$1648,'Neraca Saldo'!$B$7:$B$55,Jurnal!$I$6:$I$1648) -> 0 | G49: =+E49-F49 -> 6387409 | H49: D | I49: 13793090 | K49: =+I49-G49 -> 7405681
A50: Beban Legal | B50: 519 | C50: Beban Legal | E50: =SUMIF(Jurnal!$C$6:$C$1648,'Neraca Saldo'!$B$7:$B$55,Jurnal!$H$6:$H$1648) -> 0 | F50: =SUMIF(Jurnal!$C$6:$C$1648,'Neraca Saldo'!$B$7:$B$55,Jurnal!$I$6:$I$1648) -> 0 | G50: =+E50-F50 -> 0 | H50: D | I50: 0 | K50: =+I50-G50 -> 0
A51: Beban Perlengkapan | B51: 520 | C51: Beban Perlengkapan | E51: =SUMIF(Jurnal!$C$6:$C$1648,'Neraca Saldo'!$B$7:$B$55,Jurnal!$H$6:$H$1648) -> 11101290 | F51: =SUMIF(Jurnal!$C$6:$C$1648,'Neraca Saldo'!$B$7:$B$55,Jurnal!$I$6:$I$1648) -> 33000 | G51: =+E51-F51 -> 11068290 | H51: D | I51: 8314823 | K51: =+I51-G51 -> -2753467
A52: Beban Biaya Bank | B52: 521 | C52: Beban Biaya Bank | E52: =SUMIF(Jurnal!$C$6:$C$1648,'Neraca Saldo'!$B$7:$B$55,Jurnal!$H$6:$H$1648) -> 189682 | F52: =SUMIF(Jurnal!$C$6:$C$1648,'Neraca Saldo'!$B$7:$B$55,Jurnal!$I$6:$I$1648) -> 0 | G52: =+E52-F52 -> 189682 | H52: D | I52: 381766 | K52: =+I52-G52 -> 192084
A53: Beban Pajak | B53: 522 | C53: Beban Pajak | E53: =SUMIF(Jurnal!$C$6:$C$1648,'Neraca Saldo'!$B$7:$B$55,Jurnal!$H$6:$H$1648) -> 23598627 | F53: =SUMIF(Jurnal!$C$6:$C$1648,'Neraca Saldo'!$B$7:$B$55,Jurnal!$I$6:$I$1648) -> 0 | G53: =+E53-F53 -> 23598627 | H53: D | I53: 7266944.4 | K53: =+I53-G53 -> -16331683
A54: Beban RAT | B54: 523 | C54: Beban RAT | E54: =SUMIF(Jurnal!$C$6:$C$1648,'Neraca Saldo'!$B$7:$B$55,Jurnal!$H$6:$H$1648) -> 38672142 | F54: =SUMIF(Jurnal!$C$6:$C$1648,'Neraca Saldo'!$B$7:$B$55,Jurnal!$I$6:$I$1648) -> 0 | G54: =+E54-F54 -> 38672142 | H54: D
E56: =SUM(E8:E55) -> 1.649797e+10 | F56: =SUM(F8:F55) -> 16688904710 | G56: =SUM(G8:G55) -> 2.9926876e+09
E58: =+E56-F56 -> -1.9093435e+08 | G58: =SUM(G36:G40) -> 1591810987
G59: =SUM(G43:G54) -> 3.2664693e+08
G60: =G58-G59 -> 1.2651641e+09

Sheet Neraca 
B2: KOPERASI KARYAWAN
B3: AEROSPACE
B4: N E R A C A
B5: per 31 Desember 2025
B7: Nama Perkiraan | E7: 2025 | G7: Nama Perkiraan | J7: 2025
B11: AKTIVA LANCAR | G11: HUTANG LANCAR
C13: Kas & Bank | E13: =SUMIF('Neraca Saldo'!$A$8:$A$55,'Neraca '!C13,'Neraca Saldo'!$G$8:$G$55) -> 30668651 | H13: Simpanan Karyawan | J13: =SUMIF('Neraca Saldo'!$A$8:$A$55,'Neraca '!H13,'Neraca Saldo'!$G$8:$G$55) -> -3294007563
C14: Piutang Anggota | E14: =SUMIF('Neraca Saldo'!$A$8:$A$55,'Neraca '!C14,'Neraca Saldo'!$G$8:$G$55) -> 3.0133326e+09 | H14: Hutang Lain-lain | J14: =SUMIF('Neraca Saldo'!$A$8:$A$55,'Neraca '!H14,'Neraca Saldo'!$G$8:$G$55) -> 0
C15: Piutang Jasa | E15: =SUMIF('Neraca Saldo'!$A$8:$A$55,'Neraca '!C15,'Neraca Saldo'!$G$8:$G$55) -> 0 | H15: Dana Sosial | J15: =SUMIF('Neraca Saldo'!$A$8:$A$55,'Neraca '!H15,'Neraca Saldo'!$G$8:$G$55) -> 0
C16: Piutang Unit Simpan Pinjam | E16: =SUMIF('Neraca Saldo'!$A$8:$A$55,'Neraca '!C16,'Neraca Saldo'!$G$8:$G$55) -> 244350188 | H16: Hutang SHU | J16: =SUMIF('Neraca Saldo'!$A$8:$A$55,'Neraca '!H16,'Neraca Saldo'!$G$8:$G$55) -> 0
C17: Piutang Unit Toko | E17: =SUMIF('Neraca Saldo'!$A$8:$A$55,'Neraca '!C17,'Neraca Saldo'!$G$8:$G$55) -> 1.4274476e+08 | H17: Hutang SPN | J17: =SUMIF('Neraca Saldo'!$A$8:$A$55,'Neraca '!H17,'Neraca Saldo'!$G$8:$G$55) -> 0
C18: Piutang Pengadaan | E18: =SUMIF('Neraca Saldo'!$A$8:$A$55,'Neraca '!C18,'Neraca Saldo'!$G$8:$G$55) -> 65170235 | H18: Hutang Pajak | J18: =SUMIF('Neraca Saldo'!$A$8:$A$55,'Neraca '!H18,'Neraca Saldo'!$G$8:$G$55) -> -23597627
C19: Piutang Collins | E19: =SUMIF('Neraca Saldo'!$A$8:$A$55,'Neraca '!C19,'Neraca Saldo'!$G$8:$G$55) -> 0
C20: Persediaan Barang Dagangan | E20: =SUMIF('Neraca Saldo'!$A$8:$A$55,'Neraca '!C20,'Neraca Saldo'!$G$8:$G$55) -> 19567477
C22: Total | E22: =SUM(E13:E21) -> 3.5158339e+09 | H22: Total | J22: =SUM(J13:J21) -> -3.3176052e+09
B24: AKTIVA TETAP | G24: MODAL
C26: Nilai Perolehan | E26: =SUMIF('Neraca Saldo'!$A$8:$A$55,'Neraca '!C26,'Neraca Saldo'!$G$8:$G$55) -> 0 | H26: Modal Awal | J26: =SUMIF('Neraca Saldo'!$A$8:$A$55,'Neraca '!H26,'Neraca Saldo'!$G$8:$G$55) -> 0
C27: Akumulasi Penyusutan | E27: =SUMIF('Neraca Saldo'!$A$8:$A$55,'Neraca '!C27,'Neraca Saldo'!$G$8:$G$55) -> 0 | H27: (Laba)/Rugi ditahan | J27: =SUMIF('Neraca Saldo'!$A$8:$A$55,'Neraca '!H27,'Neraca Saldo'!$G$8:$G$55) -> -1.1879333e+08
C28: Total | E28: =SUM(E26:E27) -> 0 | H28: SHU yang dibagikan | J28: =SUMIF('Neraca Saldo'!$A$8:$A$55,'Neraca '!H28,'Neraca Saldo'!$G$8:$G$55) -> 111499000
H29: Laba/(Rugi) Periode Berjalan | J29: =+'Neraca Saldo'!G33 -> -1.9093435e+08
B30: AKTIVA LAINNYA | H30: Total | J30: =+J26+J27+J28+J29 -> -1.9822868e+08
C32: Pekerjaan dlm Proses | E32: =SUMIF('Neraca Saldo'!$A$8:$A$55,'Neraca '!C32,'Neraca Saldo'!$G$8:$G$55) -> 0
L33: =E35-L35 -> 2.9767906e+09
B35: Grand Total | E35: =+E22+E28+E32 -> 3.5158339e+09 | G35: Grand Total | J35: =+J22+J30 -> -3.5158339e+09 | L35: 5.3904325e+08
L37: =J35+E35 -> -0.24855661
C38: Bandung 31 Desember 2023
C39: Dibuat Oleh, | H39: Diketahui Oleh,
C43: Candra Warsita | H43: Ari Saepudin
C45: =+B2 -> KOPERASI KARYAWAN
C46: =+B3 -> AEROSPACE
C47: Laba / Rugi
C48: =+B5 -> per 31 Desember 2025
C50: Laba / Rugi
C54: Pendapatan
C56: Pendapatan Toko | E56: =SUMIF('Neraca Saldo'!$A$8:$A$55,'Neraca '!C56,'Neraca Saldo'!$G$8:$G$55) -> 1227746947
C57: Harga Pokok Penjualan | E57: =SUMIF('Neraca Saldo'!$A$8:$A$55,'Neraca '!C57,'Neraca Saldo'!$G$8:$G$55) -> 1.0742297e+09
C58: Laba Kotor Toko | E58: =E56-E57 -> 1.5351723e+08
C60: Pendapatan Jasa Pinjaman | E60: =SUMIF('Neraca Saldo'!$A$8:$A$55,'Neraca '!C60,'Neraca Saldo'!$G$8:$G$55) -> 213716844
C61: Pendapatan Jasa Pengadaan | E61: =SUMIF('Neraca Saldo'!$A$8:$A$55,'Neraca '!C61,'Neraca Saldo'!$G$8:$G$55) -> 148603306
C63: Total Pendapatan | E63: =E58+E60+E61 -> 5.1583738e+08
C65: Beban
C67: Beban Jasa | E67: =SUMIF('Neraca Saldo'!$A$8:$A$55,'Neraca '!C67,'Neraca Saldo'!$G$8:$G$55) -> 5529757
C68: Beban Pengurus dan Anggota | E68: =SUMIF('Neraca Saldo'!$A$8:$A$55,'Neraca '!C68,'Neraca Saldo'!$G$8:$G$55) -> 105032332
C69: Beban Lain-lain | E69: =SUMIF('Neraca Saldo'!$A$8:$A$55,'Neraca '!C69,'Neraca Saldo'!$G$8:$G$55) -> 76113
C70: Beban Gaji | E70: =SUMIF('Neraca Saldo'!$A$8:$A$55,'Neraca '!C70,'Neraca Saldo'!$G$8:$G$55) -> 126860000
C71: Beban ATK | E71: =SUMIF('Neraca Saldo'!$A$8:$A$55,'Neraca '!C71,'Neraca Saldo'!$G$8:$G$55) -> 3142573
C72: Beban Transport | E72: =SUMIF('Neraca Saldo'!$A$8:$A$55,'Neraca '!C72,'Neraca Saldo'!$G$8:$G$55) -> 6090000
C73: Beban Training | E73: =SUMIF('Neraca Saldo'!$A$8:$A$55,'Neraca '!C73,'Neraca Saldo'!$G$8:$G$55) -> 6387409
C74: Beban Legal | E74: =SUMIF('Neraca Saldo'!$A$8:$A$55,'Neraca '!C74,'Neraca Saldo'!$G$8:$G$55) -> 0
C75: Beban Perlengkapan | E75: =SUMIF('Neraca Saldo'!$A$8:$A$55,'Neraca '!C75,'Neraca Saldo'!$G$8:$G$55) -> 11068290
C76: Beban Biaya Bank | E76: =SUMIF('Neraca Saldo'!$A$8:$A$55,'Neraca '!C76,'Neraca Saldo'!$G$8:$G$55) -> 189682
C77: Beban RAT | E77: =SUMIF('Neraca Saldo'!$A$8:$A$55,'Neraca '!C77,'Neraca Saldo'!$G$8:$G$55) -> 38672142
C78: Total Beban | E78: =SUM(E67:E77) -> 303048298
H79: 31E | I79: UMKM
C80: Pendapatan Lain-lain | E80: =SUMIF('Neraca Saldo'!$A$8:$A$55,'Neraca '!C80,'Neraca Saldo'!$G$8:$G$55) -> 1743890 | H80: =E82*50%*22% -> 23598627 | I80: =E56*0.5% -> 6138734.7 | J80: =E60*0.5% -> 1068584.2
J81: =E61*0.5% -> 743016.53
C82: Laba / (Rugi) Sebelum Pajak | E82: =E63-E78+E80 -> 2.1453297e+08
C83: Beban Pajak | E83: =SUMIF('Neraca Saldo'!$A$8:$A$55,'Neraca '!C83,'Neraca Saldo'!$G$8:$G$55) -> 23598627
E84: =E82-E83 -> 1.9093435e+08

Sheet SHU
C5: 212
A6: KOPERASI KARYAWAN | C6: 112
A7: AEROSPACE
A8: Tabel Persentase SHU
A9: per 31 Desember 2023
A11: 2010 - 2011
A12: Laba | B12: Laba Ditahan | C12: Deviden | D12: Jasa | E12: Pengurus | F12: Dana Sosial | H12: Total
A13: =+'Neraca '!E82 -> 2.1453297e+08 | B13: 0.25 | C13: 0.25 | D13: 0.25 | E13: 0.225 | F13: 0.025 | H13: =SUM(B13:F13) -> 1
A14: Total | B14: =+B13*A13 -> 53633244 | C14: =+C13*A13 -> 53633244 | D14: =+D13*A13 -> 53633244 | E14: =+E13*A13 -> 48269919 | F14: =+F13*A13 -> 5363324.4 | H14: =SUM(B14:F14) -> 2.1453297e+08
A16: 2023
A17: Laba | B17: Laba Ditahan | C17: Deviden | D17: Jasa | E17: Pengurus | F17: Dana Pendidikan | G17: Dana Pembangunan | H17: Total
A18: ='Neraca '!E84 -> 1.9093435e+08 | B18: 0.2 | C18: 0.2 | D18: 0.3 | E18: 0.15 | F18: 0.1 | G18: 0.05 | H18: =SUM(B18:G18) -> 1
A19: Total | B19: =$A$18*B18 -> 38186869 | C19: =$A$18*C18 -> 38186869 | D19: =$A$18*D18 -> 57280304 | E19: =$A$18*E18 -> 28640152 | F19: =$A$18*F18 -> 19093435 | G19: =$A$18*G18 -> 9546717.4 | H19: =SUM(B19:G19) -> 1.9093435e+08
C20: 584000
C21: =C19-C20 -> 37602869
A22: 2010 - 2011
A23: Laba | B23: Laba Ditahan | C23: Deviden | D23: Jasa | E23: Pengurus | F23: Dana Sosial | H23: Total
A24: 1503457 | B24: 0.25 | C24: 0.25 | D24: 0.25 | E24: 0.225 | F24: 0.025 | H24: 1
A25: Total | B25: =+B24*A24 -> 375864.25 | C25: =+C24*A24 -> 375864.25 | D25: =+D24*A24 -> 375864.25 | E25: =+E24*A24 -> 338277.83 | F25: =+F24*A24 -> 37586.425 | H25: =SUM(B25:F25) -> 1503457
A27: Simulasi Pembagian SHU Pengurus
A28: 2020
A29: Nama | B29: NPP | C29: % Kontribusi | D29: SHU Pengurus
A30: A | C30: =100%/9 -> 0.11111111 | D30: =$E$19*C30 -> 3182239.1
A31: B | C31: =100%/9 -> 0.11111111 | D31: =$E$19*C31 -> 3182239.1
A32: C | C32: =100%/9 -> 0.11111111 | D32: =$E$19*C32 -> 3182239.1
A33: D | C33: =100%/9 -> 0.11111111 | D33: =$E$19*C33 -> 3182239.1
A34: E | C34: =100%/9 -> 0.11111111 | D34: =$E$19*C34 -> 3182239.1
A35: F | C35: =100%/9 -> 0.11111111 | D35: =$E$19*C35 -> 3182239.1
A36: G | C36: =100%/9 -> 0.11111111 | D36: =$E$19*C36 -> 3182239.1
A37: H | C37: =100%/9 -> 0.11111111 | D37: =$E$19*C37 -> 3182239.1
A38: I | C38: =100%/9 -> 0.11111111 | D38: =$E$19*C38 -> 3182239.1
A39: Total | B39: =SUM(B30:B38) -> 0 | C39: =SUM(C30:C38) -> 1 | D39: =SUM(D30:D38) -> 28640152
H290: 200000
E291: Transport dan Lumpsump Nurdin untuk pembelian parcel
B292: 45723 | C292: 515 | E292: Pembayaran Gaji Pengurus dan Pengawas Jan - Mar 2025 | F292: Bank | H292: 11600000
B293: 45723 | C293: 111 | E293: Pembayaran Gaji Pengurus dan Pengawas Jan - Mar 2025 | F293: Bank
B294: 45723 | E294: Tabungan Sukarela Candra Warsita | F294: Bank | H294: 1200000
B295: 45723 | E295: Tabungan Sukarela Candra Warsita | F295: Bank
B296: 45723 | C296: 111 | E296: Tabungan Sukarela Ayu Sheila Madjid | F296: Bank | H296: 1000000
B297: 45723 | C297: 212 | E297: Tabungan Sukarela Ayu Sheila Madjid | F297: Bank
B298: 45723 | C298: 111 | E298: Tabungan Sukarela Dian Endah Oktaviana | F298: Bank | H298: 1200000
B299: 45723 | C299: 212 | E299: Tabungan Sukarela Dian Endah Oktaviana | F299: Bank
B300: 45729 | C300: 212 | E300: Pencairan Tabungan Sukarela Noor Hidayat | F300: Petty Cash | H300: 5000000
B301: 45729 | C301: 112 | E301: Pencairan Tabungan Sukarela Noor Hidayat | F301: Petty Cash
B302: 45730 | C302: 513 | E302: Pembayaran Parcel | F302: Petty Cash | H302: 12000000
B303: 45730 | C303: 112 | E303: Pembayaran Parcel | F303: Petty Cash
B304: 45730 | H304: 11085243
B305: 45730
B306: 45730 | H306: 11085243
B307: 45730
B308: 45730 | C308: 513 | E308: Pelunasan Parcel | F308: Petty Cash | H308: 5537500
B309: 45730 | C309: 112 | E309: Pelunasan Parcel | F309: Petty Cash
B310: 45730 | C310: 521 | E310: Admin Bank pelunasan parcel | F310: Petty Cash | H310: 2500
B311: 45730 | C311: 112 | E311: Admin Bank pelunasan parcel | F311: Petty Cash
B312: 45730 | C312: 517 | E312: Transport Pengiriman Parcel | F312: Petty Cash | H312: 300000
B313: 45730 | C313: 112 | E313: Transport Pengiriman Parcel | F313: Petty Cash
B314: 45733 | C314: 212 | E314: Pencairan Tabungan Sukarela Hary Suherman | F314: Petty Cash | H314: 100000
B315: 45733 | C315: 112 | E315: Pencairan Tabungan Sukarela Hary Suherman | F315: Petty Cash
B316: 45733 | C316: 221 | E316: CSR Panti Asuhan | F316: Petty Cash | H316: 1000000
B317: 45733 | C317: 112 | E317: CSR Panti Asuhan | F317: Petty Cash
B318: 45733 | C318: 111 | E318: Tabungan Sukarela Candra Warsita | F318: Bank | H318: 15000000
B319: 45733 | C319: 212 | E319: Tabungan Sukarela Candra Warsita | F319: Bank
B320: 45733 | C320: 111 | E320: Tabungan Sukarela Dani Hadiana | F320: Bank | H320: 4000000
B321: 45733 | C321: 212 | E321: Tabungan Sukarela Dani Hadiana | F321: Bank
B322: 45734 | C322: 513 | E322: DP Harade (Bukber 2025) | F322: Petty Cash | H322: 300000
B323: 45734 | C323: 112 | E323: DP Harade (Bukber 2025) | F323: Petty Cash
B324: 45734 | C324: 517 | E324: Lumpsump for Ayu & CW to BNI and Dealer | F324: Petty Cash | H324: 500000
B325: 45734 | C325: 112 | E325: Lumpsump for Ayu & CW to BNI and Dealer | F325: Petty Cash
B326: 45740 | H326: 30000000
B327: 45740
B328: 45740 | H328: 30000000
B329: 45740
B330: 45740 | C330: 515 | E330: Pembayaran Gaji April & THR Syahla | H330: 4080000
B331: 45740 | C331: 112 | E331: Pembayaran Gaji April & THR Syahla
B332: 45740 | C332: 515 | E332: Pembayaran Gaji April & THR Zahra | H332: 3780000
B333: 45740 | C333: 112 | E333: Pembayaran Gaji April & THR Zahra
B334: 45740 | E334: Coklat Kaizen per Jan - Feb 2025 | F334: Bank | H334: 4909750
B335: 45740 | E335: Coklat Kaizen per Jan - Feb 2025 | F335: Bank
B336: 45740 | E336: INVOICE MAR 25 - Simpanan Pokok Anggota | F336: Bank | H336: 1200000
B337: 45740 | E337: INVOICE MAR 25 - Simpanan Pokok Anggota | F337: Bank
B338: 45740 | E338: INVOICE MAR 25 - Simpanan Wajib Anggota | F338: Bank | H338: 61600000
B339: 45740 | E339: INVOICE MAR 25 - Simpanan Wajib Anggota | F339: Bank
B340: 45740 | E340: INVOICE MAR 25 - Simpanan Sukarela Berjangka | F340: Bank | H340: 30187000
B341: 45740 | E341: INVOICE MAR 25 - Simpanan Sukarela Berjangka | F341: Bank
B342: 45740 | E342: INVOICE MAR 25 - Iuran Serikat Pekerja Nasional UTC | F342: Bank | H342: 5740000
B343: 45740 | E343: INVOICE MAR 25 - Iuran Serikat Pekerja Nasional UTC | F343: Bank
B344: 45740 | E344: INVOICE MAR 25 - Angsuran Pinjaman Barang | F344: Bank | H344: 61837779
B345: 45740 | E345: INVOICE MAR 25 - Angsuran Pinjaman Barang | F345: Bank
B346: 45740 | E346: INVOICE MAR 25 - Angsuran Pinjaman Uang | F346: Bank | H346: 142476167
B347: 45740 | E347: INVOICE MAR 25 - Angsuran Pinjaman Uang | F347: Bank
B348: 45740 | E348: Coklat Kaizen per Jan - Feb 2025 | F348: Bank | H348: 4909750
B349: 45740 | E349: Coklat Kaizen per Jan - Feb 2025 | F349: Bank
B350: 45740 | E350: INVOICE MAR 25 - Simpanan Sukarela Berjangka | F350: Bank | H350: 30187000
B351: 45740 | E351: INVOICE MAR 25 - Simpanan Sukarela Berjangka | F351: Bank
B352: 45740 | E352: INVOICE MAR 25 - Iuran Serikat Pekerja Nasional UTC | F352: Bank | H352: 5740000
B353: 45740 | E353: INVOICE MAR 25 - Iuran Serikat Pekerja Nasional UTC | F353: Bank
B354: 45740 | E354: INVOICE MAR 25 - Angsuran Pinjaman Barang | F354: Bank | H354: 61837779
B355: 45740 | E355: INVOICE MAR 25 - Angsuran Pinjaman Barang | F355: Bank
B356: 45740 | E356: INVOICE MAR 25 - Angsuran Pinjaman Uang | F356: Bank | H356: 142476167
B357: 45740 | E357: INVOICE MAR 25 - Angsuran Pinjaman Uang | F357: Bank
...

Sheet Distribusi SHU
A1: No | B1: No Anggota | C1: NPP | D1: Nama Anggota | E1: Total Simpanan | F1: Total Simpanan Sukarela | G1: % Kepemilikan Modal | H1: Porsi Deviden | I1: Kontribusi Jasa USP | J1: Kontribusi Jasa Pengadaan | K1: % Kontribusi Jasa | L1: Porsi Jasa | M1: SHU SEMBAKO | N1: Total SHU Diterima | O1: Rounding | P1: Total Direlease
H3: =SHU!C21 -> 37602869 | L3: =SHU!D19 -> 57280304 | M3: =SHU!C20 -> 584000
A4: 1 | B4: KKAB0001 | C4: 34000095 | D4: ARI SAEPUDIN | E4: 11750000 | F4: 0 | G4: =(E4+F4)/$E$346 -> 0.0039549639 | H4: =G4*$H$3 -> 148717.99 | I4: 0 | J4: 2486000 | K4: =(I4+J4)/($I$345+$J$345) -> 0.0068706193 | L4: =K4*$L$3 -> 393551.16 | M4: 8000 | N4: =H4+L4+M4 -> 550269.15 | O4: =P4-N4 -> 730.84797 | P4: =ROUNDUP(N4,-3) -> 551000
A5: 2 | B5: KKAB0002 | C5: 34000484 | D5: UDAN HERNAWAN | E5: 11950000 | F5: 100000 | G5: =(E5+F5)/$E$346 -> 0.0040559417 | H5: =G5*$H$3 -> 152515.05 | I5: 1410000 | J5: 3379552.5 | K5: =(I5+J5)/($I$345+$J$345) -> 0.013237004 | L5: =K5*$L$3 -> 758219.61 | M5: 0 | N5: =H5+L5+M5 -> 910734.65 | O5: =P5-N5 -> 265.34533 | P5: =ROUNDUP(N5,-3) -> 911000
A6: 3 | B6: KKAB0003 | C6: 34000653 | D6: EGY HERYANTO | E6: 12450000 | F6: 0 | G6: =(E6+F6)/$E$346 -> 0.0041905788 | H6: =G6*$H$3 -> 157577.79 | I6: 1920000 | J6: 1489500 | K6: =(I6+J6)/($I$345+$J$345) -> 0.0094229189 | L6: =K6*$L$3 -> 539747.66 | M6: 0 | N6: =H6+L6+M6 -> 697325.45 | O6: =P6-N6 -> 674.55352 | P6: =ROUNDUP(N6,-3) -> 698000
A7: 4 | B7: KKAB0004 | C7: 34000257 | D7: BUDI SEPTIYADI | E7: 12450000 | F7: 100000 | G7: =(E7+F7)/$E$346 -> 0.004224238 | H7: =G7*$H$3 -> 158843.47 | I7: 0 | J7: 0 | K7: =(I7+J7)/($I$345+$J$345) -> 0 | L7: =K7*$L$3 -> 0 | M7: 8000 | N7: =H7+L7+M7 -> 166843.47 | O7: =P7-N7 -> 156.52864 | P7: =ROUNDUP(N7,-3) -> 167000
A8: 5 | B8: KKAB0005 | C8: 34000570 | D8: ADE ASMI TRIYOSO | E8: 12450000 | F8: 0 | G8: =(E8+F8)/$E$346 -> 0.0041905788 | H8: =G8*$H$3 -> 157577.79 | I8: 1116000 | J8: 0 | K8: =(I8+J8)/($I$345+$J$345) -> 0.0030843166 | L8: =K8*$L$3 -> 176670.59 | M8: 0 | N8: =H8+L8+M8 -> 334248.38 | O8: =P8-N8 -> 751.62012 | P8: =ROUNDUP(N8,-3) -> 335000
A9: 6 | B9: KKAB0009 | C9: 34000215 | D9: CANDRA WARSITA | E9: 12450000 | F9: 21600000 | G9: =(E9+F9)/$E$346 -> 0.01146098 | H9: =G9*$H$3 -> 430965.75 | I9: 0 | J9: 1700000 | K9: =(I9+J9)/($I$345+$J$345) -> 0.0046983318 | L9: =K9*$L$3 -> 269121.87 | M9: 8000 | N9: =H9+L9+M9 -> 708087.62 | O9: =P9-N9 -> 912.37513 | P9: =ROUNDUP(N9,-3) -> 709000
A10: 7 | B10: KKAB0011 | C10: 34000203 | D10: BONNY ARIES | E10: 12350000 | F10: 100000 | G10: =(E10+F10)/$E$346 -> 0.0041905788 | H10: =G10*$H$3 -> 157577.79 | I10: 1035000 | J10: 1841125 | K10: =(I10+J10)/($I$345+$J$345) -> 0.0079488173 | L10: =K10*$L$3 -> 455310.67 | M10: 0 | N10: =H10+L10+M10 -> 612888.46 | O10: =P10-N10 -> 111.54083 | P10: =ROUNDUP(N10,-3) -> 613000
A11: 8 | B11: KKAB0012 | C11: 34000171 | D11: CEPI SETIAWAN | E11: 12450000 | F11: 0 | G11: =(E11+F11)/$E$346 -> 0.0041905788 | H11: =G11*$H$3 -> 157577.79 | I11: 0 | J11: 0 | K11: =(I11+J11)/($I$345+$J$345) -> 0 | L11: =K11*$L$3 -> 0 | M11: 0 | N11: =H11+L11+M11 -> 157577.79 | O11: =P11-N11 -> 422.21367 | P11: =ROUNDUP(N11,-3) -> 158000
A12: 9 | B12: KKAB0014 | C12: 34000511 | D12: RUSMANA | E12: 12150000 | F12: 0 | G12: =(E12+F12)/$E$346 -> 0.004089601 | H12: =G12*$H$3 -> 153780.73 | I12: 0 | J12: 0 | K12: =(I12+J12)/($I$345+$J$345) -> 0 | L12: =K12*$L$3 -> 0 | M12: 0 | N12: =H12+L12+M12 -> 153780.73 | O12: =P12-N12 -> 219.26877 | P12: =ROUNDUP(N12,-3) -> 154000
A13: 10 | B13: KKAB0015 | C13: 34000004 | D13: YAYA CAHRIA | E13: 12450000 | F13: 0 | G13: =(E13+F13)/$E$346 -> 0.0041905788 | H13: =G13*$H$3 -> 157577.79 | I13: 1200000 | J13: 2855250 | K13: =(I13+J13)/($I$345+$J$345) -> 0.011207594 | L13: =K13*$L$3 -> 641974.39 | M13: 8000 | N13: =H13+L13+M13 -> 807552.18 | O13: =P13-N13 -> 447.81894 | P13: =ROUNDUP(N13,-3) -> 808000
A14: 11 | B14: KKAB0016 | C14: 34000623 | D14: MOCH RIZAL BAHRI | E14: 12450000 | F14: 0 | G14: =(E14+F14)/$E$346 -> 0.0041905788 | H14: =G14*$H$3 -> 157577.79 | I14: 0 | J14: 0 | K14: =(I14+J14)/($I$345+$J$345) -> 0 | L14: =K14*$L$3 -> 0 | M14: 0 | N14: =H14+L14+M14 -> 157577.79 | O14: =P14-N14 -> 422.21367 | P14: =ROUNDUP(N14,-3) -> 158000
A15: 12 | B15: KKAB0017 | C15: 34000656 | D15: AGUS CAHYA SURATMAN | E15: 12450000 | F15: 0 | G15: =(E15+F15)/$E$346 -> 0.0041905788 | H15: =G15*$H$3 -> 157577.79 | I15: 0 | J15: 0 | K15: =(I15+J15)/($I$345+$J$345) -> 0 | L15: =K15*$L$3 -> 0 | M15: 8000 | N15: =H15+L15+M15 -> 165577.79 | O15: =P15-N15 -> 422.21367 | P15: =ROUNDUP(N15,-3) -> 166000
... A321: 318 | B321: KKAB0424 | C321: 34000214 | D321: FIAN NURDIAN | E321: 350000 | F321: 0 | G321: =(E321+F321)/$E$346 -> 0.00011780744 | H321: =G321*$H$3 -> 4429.8976 | I321: 0 | J321: 0 | K321: =(I321+J321)/($I$345+$J$345) -> 0 | L321: =K321*$L$3 -> 0 | M321: 0 | N321: =H321+L321+M321 -> 4429.8976 | O321: =P321-N321 -> 570.10239 | P321: =ROUNDUP(N321,-3) -> 5000
A322: 319 | B322: KALB0001 | C322: ISS | D322: NOVIA ELINDA | E322: 1950000 | F322: 0 | G322: =(E322+F322)/$E$346 -> 0.00065635571 | H322: =G322*$H$3 -> 24680.858 | I322: 0 | J322: 0 | K322: =(I322+J322)/($I$345+$J$345) -> 0 | L322: =K322*$L$3 -> 0 | M322: 0 | N322: =H322+L322+M322 -> 24680.858 | O322: =P322-N322 -> 319.1419 | P322: =ROUNDUP(N322,-3) -> 25000
A323: 320 | B323: KALB0002 | C323: ISS | D323: ANI AFRIANI | E323: 1950000 | F323: 0 | G323: =(E323+F323)/$E$346 -> 0.00065635571 | H323: =G323*$H$3 -> 24680.858 | I323: 0 | J323: 0 | K323: =(I323+J323)/($I$345+$J$345) -> 0 | L323: =K323*$L$3 -> 0 | M323: 0 | N323: =H323+L323+M323 -> 24680.858 | O323: =P323-N323 -> 319.1419 | P323: =ROUNDUP(N323,-3) -> 25000
A324: 321 | B324: KALB0003 | C324: NWK | D324: AGUS SETIAWAN | E324: 1950000 | F324: 0 | G324: =(E324+F324)/$E$346 -> 0.00065635571 | H324: =G324*$H$3 -> 24680.858 | I324: 0 | J324: 0 | K324: =(I324+J324)/($I$345+$J$345) -> 0 | L324: =K324*$L$3 -> 0 | M324: 0 | N324: =H324+L324+M324 -> 24680.858 | O324: =P324-N324 -> 319.1419 | P324: =ROUNDUP(N324,-3) -> 25000
A325: 322 | B325: KALB0004 | C325: ISS | D325: IWAN | E325: 1750000 | F325: 0 | G325: =(E325+F325)/$E$346 -> 0.00058903718 | H325: =G325*$H$3 -> 22149.488 | I325: 0 | J325: 0 | K325: =(I325+J325)/($I$345+$J$345) -> 0 | L325: =K325*$L$3 -> 0 | M325: 0 | N325: =H325+L325+M325 -> 22149.488 | O325: =P325-N325 -> 850.51196 | P325: =ROUNDUP(N325,-3) -> 23000
A326: 323 | B326: KALB0005 | C326: ISS | D326: RAGIL SANTOSO | E326: 1750000 | F326: 0 | G326: =(E326+F326)/$E$346 -> 0.00058903718 | H326: =G326*$H$3 -> 22149.488 | I326: 0 | J326: 0 | K326: =(I326+J326)/($I$345+$J$345) -> 0 | L326: =K326*$L$3 -> 0 | M326: 0 | N326: =H326+L326+M326 -> 22149.488 | O326: =P326-N326 -> 850.51196 | P326: =ROUNDUP(N326,-3) -> 23000
A327: 324 | B327: KALB0006 | C327: ISS | D327: EGIH SOPIAN | E327: 1750000 | F327: 0 | G327: =(E327+F327)/$E$346 -> 0.00058903718 | H327: =G327*$H$3 -> 22149.488 | I327: 0 | J327: 0 | K327: =(I327+J327)/($I$345+$J$345) -> 0 | L327: =K327*$L$3 -> 0 | M327: 0 | N327: =H327+L327+M327 -> 22149.488 | O327: =P327-N327 -> 850.51196 | P327: =ROUNDUP(N327,-3) -> 23000
A328: 325 | B328: KALB0007 | C328: ISS | D328: INDAH OKTAVIANI | E328: 1750000 | F328: 0 | G328: =(E328+F328)/$E$346 -> 0.00058903718 | H328: =G328*$H$3 -> 22149.488 | I328: 0 | J328: 0 | K328: =(I328+J328)/($I$345+$J$345) -> 0 | L328: =K328*$L$3 -> 0 | M328: 0 | N328: =H328+L328+M328 -> 22149.488 | O328: =P328-N328 -> 850.51196 | P328: =ROUNDUP(N328,-3) -> 23000
A329: 326 | B329: KALB0008 | C329: JBL | D329: DEDENG ROSADI | E329: 1750000 | F329: 0 | G329: =(E329+F329)/$E$346 -> 0.00058903718 | H329: =G329*$H$3 -> 22149.488 | I329: 0 | J329: 0 | K329: =(I329+J329)/($I$345+$J$345) -> 0 | L329: =K329*$L$3 -> 0 | M329: 0 | N329: =H329+L329+M329 -> 22149.488 | O329: =P329-N329 -> 850.51196 | P329: =ROUNDUP(N329,-3) -> 23000
A330: 327 | B330: KALB0009 | C330: JBL | D330: EKASAKTI SETIAWAN | E330: 1750000 | F330: 0 | G330: =(E330+F330)/$E$346 -> 0.00058903718 | H330: =G330*$H$3 -> 22149.488 | I330: 0 | J330: 0 | K330: =(I330+J330)/($I$345+$J$345) -> 0 | L330: =K330*$L$3 -> 0 | M330: 0 | N330: =H330+L330+M330 -> 22149.488 | O330: =P330-N330 -> 850.51196 | P330: =ROUNDUP(N330,-3) -> 23000
A331: 328 | B331: KALB0010 | C331: ISS | D331: DERIKO ALAMSYAH PUTRA | E331: 1750000 | F331: 0 | G331: =(E331+F331)/$E$346 -> 0.00058903718 | H331: =G331*$H$3 -> 22149.488 | I331: 0 | J331: 0 | K331: =(I331+J331)/($I$345+$J$345) -> 0 | L331: =K331*$L$3 -> 0 | M331: 0 | N331: =H331+L331+M331 -> 22149.488 | O331: =P331-N331 -> 850.51196 | P331: =ROUNDUP(N331,-3) -> 23000
A332: 329 | B332: KALB0011 | C332: JBL | D332: RIAN KASRIAN | E332: 1750000 | F332: 0 | G332: =(E332+F332)/$E$346 -> 0.00058903718 | H332: =G332*$H$3 -> 22149.488 | I332: 0 | J332: 0 | K332: =(I332+J332)/($I$345+$J$345) -> 0 | L332: =K332*$L$3 -> 0 | M332: 0 | N332: =H332+L332+M332 -> 22149.488 | O332: =P332-N332 -> 850.51196 | P332: =ROUNDUP(N332,-3) -> 23000
A333: 330 | B333: KALB0012 | C333: ISS | D333: ALEX SUPRIATNA | E333: 1750000 | F333: 0 | G333: =(E333+F333)/$E$346 -> 0.00058903718 | H333: =G333*$H$3 -> 22149.488 | I333: 0 | J333: 0 | K333: =(I333+J333)/($I$345+$J$345) -> 0 | L333: =K333*$L$3 -> 0 | M333: 0 | N333: =H333+L333+M333 -> 22149.488 | O333: =P333-N333 -> 850.51196 | P333: =ROUNDUP(N333,-3) -> 23000
... A344: 341 | B344: KALB0023 | C344: KAB | D344: ZAHRA NUR SYIFA | E344: 750000 | F344: 0 | G344: =(E344+F344)/$E$346 -> 0.0002524445 | H344: =G344*$H$3 -> 9492.6377 | I344: 0 | J344: 0 | K344: =(I344+J344)/($I$345+$J$345) -> 0 | L344: =K344*$L$3 -> 0 | M344: 0 | N344: =H344+L344+M344 -> 9492.6377 | O344: =P344-N344 -> 507.36227 | P344: =ROUNDUP(N344,-3) -> 10000
E345: =SUM(E4:E344) -> 2870950000 | F345: =SUM(F4:F344) -> 100000000 | G345: =SUM(G4:G344) -> 1 | H345: =SUM(H4:H282) -> 36120752 | I345: =SUM(I4:I344) -> 2.1897239e+08 | J345: =SUM(J4:J344) -> 1.4285817e+08 | K345: =SUM(K4:K344) -> 1 | L345: =SUM(L4:L344) -> 57280304 | M345: =SUM(M4:M344) -> 584000 | N345: =SUM(N4:N344) -> 95467174 | O345: =SUM(O4:O344) -> 175826.45 | P345: =SUM(P4:P344) -> 95643000
E346: =E345+F345 -> 2970950000 | P346: 95467174
D347: Jasa anggota yang sudah keluar | I347: =1066667+711333+135000+405000+416667 -> 2734667 | J347: =655000+279167+1310000+490000+375000 -> 3109167 | P347: =P345-P346 -> 175826.45
I348: =I345+I347 -> 2.2170706e+08 | J348: =J345+J347 -> 1.4596734e+08
I349: =' usp (dian)'!D169 -> 1088000
D350: Gap | I350: =I349-I348 -> -2.2061906e+08 | J350: =J349-J348 -> -1.4596734e+08

Sheet LIST DISTRIBUSI SHU
A1: LIST DISTRIBUSI SISA HASIL USAHA (SHU) TAHUN BUKU 2025
A2: No | B2: No Anggota | C2: NPP | D2: Nama Anggota | E2: TOTAL SHU DITERIMA | F2: SIGN
A3: 1 | B3: KKAB0001 | C3: 34000095 | D3: ARI SAEPUDIN | E3: 551000
A4: 2 | B4: KKAB0002 | C4: 34000484 | D4: UDAN HERNAWAN | E4: 911000
A5: 3 | B5: KKAB0003 | C5: 34000653 | D5: EGY HERYANTO | E5: 698000
A6: 4 | B6: KKAB0004 | C6: 34000257 | D6: BUDI SEPTIYADI | E6: 167000
A7: 5 | B7: KKAB0005 | C7: 34000570 | D7: ADE ASMI TRIYOSO | E7: 335000
A8: 6 | B8: KKAB0009 | C8: 34000215 | D8: CANDRA WARSITA | E8: 709000
A9: 7 | B9: KKAB0011 | C9: 34000203 | D9: BONNY ARIES | E9: 613000
A10: 8 | B10: KKAB0012 | C10: 34000171 | D10: CEPI SETIAWAN | E10: 158000
A11: 9 | B11: KKAB0014 | C11: 34000511 | D11: RUSMANA | E11: 154000
A12: 10 | B12: KKAB0015 | C12: 34000004 | D12: YAYA CAHRIA | E12: 808000
A13: 11 | B13: KKAB0016 | C13: 34000623 | D13: MOCH RIZAL BAHRI | E13: 158000
A14: 12 | B14: KKAB0017 | C14: 34000656 | D14: AGUS CAHYA SURATMAN | E14: 166000
... A320: 324 | B320: KKAB0424 | C320: 34000214 | D320: FIAN NURDIAN | E320: 5000
A321: 325 | B321: KALB0001 | C321: ISS | D321: NOVIA ELINDA | E321: 25000
A322: 326 | B322: KALB0002 | C322: ISS | D322: ANI AFRIANI | E322: 25000
A323: 327 | B323: KALB0003 | C323: NWK | D323: AGUS SETIAWAN | E323: 25000
A324: 328 | B324: KALB0004 | C324: ISS | D324: IWAN | E324: 23000
A325: 329 | B325: KALB0005 | C325: ISS | D325: RAGIL SANTOSO | E325: 23000
A326: 330 | B326: KALB0006 | C326: ISS | D326: EGIH SOPIAN | E326: 23000
A327: 331 | B327: KALB0007 | C327: ISS | D327: INDAH OKTAVIANI | E327: 23000
A328: 332 | B328: KALB0008 | C328: JBL | D328: DEDENG ROSADI | E328: 23000
A329: 333 | B329: KALB0009 | C329: JBL | D329: EKASAKTI SETIAWAN | E329: 23000
A330: 334 | B330: KALB0010 | C330: ISS | D330: DERIKO ALAMSYAH PUTRA | E330: 23000
A331: 335 | B331: KALB0011 | C331: JBL | D331: RIAN KASRIAN | E331: 23000
A332: 336 | B332: KALB0012 | C332: ISS | D332: ALEX SUPRIATNA | E332: 23000
... A343: 347 | B343: KALB0023 | C343: KAB | D343: ZAHRA NUR SYIFA | E343: 10000
E344: =SUM(E3:E343) -> 95643000

Sheet LIST DISTRIBUSI PARCEL
A1: LIST DISTRIBUSI PARCEL LEBARAN 2024 (1445H)
A3: No | B3: No Anggota | C3: NPP | D3: Nama Anggota | E3: STATUS | F3: SIGN
A4: 1 | B4: KKAB0001 | C4: 34000095 | D4: ARI SAEPUDIN | E4: ANGGOTA
A5: 2 | B5: KKAB0002 | C5: 34000484 | D5: UDAN HERNAWAN | E5: ANGGOTA
A6: 3 | B6: KKAB0003 | C6: 34000653 | D6: EGY HERYANTO | E6: ANGGOTA
A7: 4 | B7: KKAB0004 | C7: 34000257 | D7: BUDI SEPTIYADI | E7: ANGGOTA
A8: 5 | B8: KKAB0005 | C8: 34000570 | D8: ADE ASMI TRIYOSO | E8: ANGGOTA
A9: 6 | B9: KKAB0009 | C9: 34000215 | D9: CANDRA WARSITA | E9: ANGGOTA
A10: 7 | B10: KKAB0011 | C10: 34000203 | D10: BONNY ARIES | E10: ANGGOTA
A11: 8 | B11: KKAB0012 | C11: 34000171 | D11: CEPI SETIAWAN | E11: ANGGOTA
A12: 9 | B12: KKAB0014 | C12: 34000511 | D12: RUSMANA | E12: ANGGOTA
A13: 10 | B13: KKAB0015 | C13: 34000004 | D13: YAYA CAHRIA | E13: ANGGOTA
A14: 11 | B14: KKAB0016 | C14: 34000623 | D14: MOCH RIZAL BAHRI | E14: ANGGOTA
A15: 12 | B15: KKAB0017 | C15: 34000656 | D15: AGUS CAHYA SURATMAN | E15: ANGGOTA
A16: 13 | B16: KKAB0018 | C16: 34000130 | D16: AHMAD YADI | E16: ANGGOTA
A17: 14 | B17: KKAB0022 | C17: 34000692 | D17: IMAM NURZAMAN | E17: ANGGOTA
A18: 15 | B18: KKAB0023 | C18: 34000514 | D18: ADIFIA PRAMANA | E18: ANGGOTA
A19: 16 | B19: KKAB0024 | C19: 34000392 | D19: YUS YUSUP | E19: ANGGOTA
A20: 17 | B20: KKAB0025 | C20: 34000510 | D20: GALIH PRASETYO | E20: ANGGOTA
A21: 18 | B21: KKAB0026 | C21: 34000469 | D21: JULI AGUS SETIAWAN | E21: ANGGOTA
A22: 19 | B22: KKAB0028 | C22: 34000158 | D22: UTANG SUMARNA | E22: ANGGOTA
A23: 20 | B23: KKAB0029 | C23: 34000346 | D23: IRAWAN JUMYATI | E23: ANGGOTA
A24: 21 | B24: KKAB0030 | C24: 34000320 | D24: ASEP IPAN SOPIAN | E24: ANGGOTA
... A51: 48 | B51: KKAB0068 | C51: 34000486 | D51: SUNDARA SANDI | E51: ANGGOTA
A52: 49 | B52: KKAB0070 | C52: 34000564 | D52: TONY RAMANDA | E52: ANGGOTA
A53: 50 | B53: KKAB0073 | C53: 34000258 | D53: M. DIXIE PERMANA | E53: ANGGOTA
A54: 51 | B54: KKAB0075 | C54: 34000771 | D54: RONI IRAWAN | E54: ANGGOTA
A55: 52 | B55: KKAB0076 | C55: 34000640 | D55: HENDRIK TURMIDI HASIM | E55: ANGGOTA
A56: 53 | B56: KKAB0079 | C56: 34000492 | D56: IYEP SUTISNA | E56: ANGGOTA
A57: 54 | B57: KKAB0081 | C57: 34000488 | D57: M RAMDAN PRATAMA | E57: ANGGOTA
A58: 55 | B58: KKAB0086 | C58: 34000363 | D58: REDI NURHADI | E58: ANGGOTA
A59: 56 | B59: KKAB0088 | C59: 34000277 | D59: YUDI WAHYUDIN | E59: ANGGOTA
A60: 57 | B60: KKAB0089 | C60: 34000446 | D60: MARKUWAT | E60: ANGGOTA
A61: 58 | B61: KKAB0090 | C61: 34000160 | D61: YADI CAHYADI | E61: ANGGOTA
A62: 59 | B62: KKAB0091 | C62: 34000100 | D62: ASEP RUHIMAT | E62: ANGGOTA
A63: 60 | B63: KKAB0094 | C63: 34000631 | D63: ASEP SUKMANA | E63: ANGGOTA
A64: 61 | B64: KKAB0096 | C64: 34000396 | D64: TRI OGA NUGRAHA | E64: ANGGOTA
A65: 62 | B65: KKAB0097 | C65: 34000188 | D65: ANDRI SAPUTRA | E65: ANGGOTA
A66: 63 | B66: KKAB0098 | C66: 34000487 | D66: KELIK SUSANTO | E66: ANGGOTA
A67: 64 | B67: KKAB0099 | C67: 34000476 | D67: PIRMAN SUKARMAN | E67: ANGGOTA
A68: 65 | B68: KKAB0100 | C68: 34000579 | D68: EGIET REDITA | E68: ANGGOTA
A69: 66 | B69: KKAB0103 | C69: 34000695 | D69: IWAN GUNAWAN | E69: ANGGOTA
A70: 67 | B70: KKAB0104 | C70: 34000455 | D70: IWAN SUHARJAT | E70: ANGGOTA
A71: 68 | B71: KKAB0106 | C71: 34000303 | D71: JAMALUDIN ROSIHAN | E71: ANGGOTA
A72: 69 | B72: KKAB0107 | C72: 34000569 | D72: GILANG ASHARI | E72: ANGGOTA
A73: 70 | B73: KKAB0109 | C73: 34000503 | D73: DENI MULYADI RAHMAN | E73: ANGGOTA
A74: 71 | B74: KKAB0110 | C74: 34000527 | D74: CAHYA RAMDANI | E74: ANGGOTA
A75: 72 | B75: KKAB0111 | C75: 34000210 | D75: ASEP SOPYAN | E75: ANGGOTA
A76: 73 | B76: KKAB0113 | C76: 34000115 | D76: MUHAMMAD ROMI | E76: ANGGOTA
A77: 74 | B77: KKAB0115 | C77: 34000124 | D77: MIRPANUDIN | E77: ANGGOTA
A78: 75 | B78: KKAB0116 | C78: 34000131 | D78: DANI MAULANA | E78: ANGGOTA
A79: 76 | B79: KKAB0117 | C79: 34000516 | D79: AGUNG TAQWA JANUAR | E79: ANGGOTA
A80: 77 | B80: KKAB0119 | C80: 34000230 | D80: TARMAN | E80: ANGGOTA
A81: 78 | B81: KKAB0120 | C81: 34000050 | D81: HERI GUNAWAN | E81: ANGGOTA
A82: 79 | B82: KKAB0122 | C82: 34000150 | D82: AJAT SUDRAJAT | E82: ANGGOTA
A83: 80 | B83: KKAB0123 | C83: 34000404 | D83: AHMAD SUPRIYADI | E83: ANGGOTA
A84: 81 | B84: KKAB0125 | C84: 34000499 | D84: GUNAWAN JAYANA | E84: ANGGOTA
A85: 82 | B85: KKAB0126 | C85: 34000316 | D85: IRVAN FEBRIANSYAH | E85: ANGGOTA
A86: 83 | B86: KKAB0127 | C86: 34000422 | D86: INDRA ISKANDAR | E86: ANGGOTA
A87: 84 | B87: KKAB0129 | C87: 34000398 | D87: ANDY KUSUMAYADI | E87: ANGGOTA
A88: 85 | B88: KKAB0130 | C88: 34000462 | D88: PRAMONO | E88: ANGGOTA
A89: 86 | B89: KKAB0132 | C89: 34000119 | D89: ASEP PERMANA | E89: ANGGOTA
A90: 87 | B90: KKAB0133 | C90: 34000217 | D90: DWI AGUS PURNOMO | E90: ANGGOTA
A91: 88 | B91: KKAB0136 | C91: 34000252 | D91: YUDHA RAHMAT A | E91: ANGGOTA
A92: 89 | B92: KKAB0137 | C92: 34000593 | D92: IWAN SETIAWAN | E92: ANGGOTA
A93: 90 | B93: KKAB0138 | C93: 34000582 | D93: IWAN NURCAHYA | E93: ANGGOTA
A94: 91 | B94: KKAB0139 | C94: 34000336 | D94: WAHYU SARIYANTO | E94: ANGGOTA
A95: 92 | B95: KKAB0143 | C95: 34000221 | D95: HENDAR HAMZAH | E95: ANGGOTA
... A107: 104 | B107: KKAB0160 | C107: 34000224 | D107: M. GILANG RAMADHAN | E107: ANGGOTA
A108: 105 | B108: KKAB0161 | C108: 34000524 | D108: HENDRA FIRMANSYAH | E108: ANGGOTA
A109: 106 | B109: KKAB0163 | C109: 34000566 | D109: ADI WARDHAYA | E109: ANGGOTA
A110: 107 | B110: KKAB0164 | C110: 34000013 | D110: SUKADI | E110: ANGGOTA
A111: 108 | B111: KKAB0168 | C111: 34000077 | D111: DENI SUHENDAR | E111: ANGGOTA
A112: 109 | B112: KKAB0171 | C112: 34000757 | D112: GUMILAR MUHAMAD P | E112: ANGGOTA
A113: 110 | B113: KKAB0172 | C113: 34000012 | D113: WAHIDIN | E113: ANGGOTA
A114: 111 | B114: KKAB0176 | C114: 34000794 | D114: GANDI | E114: ANGGOTA
A115: 112 | B115: KKAB0177 | C115: 34000850 | D115: DIAN ENDAH OKTAVIANA | E115: ANGGOTA
A116: 113 | B116: KKAB0180 | C116: 34000513 | D116: NOVI SUSANTI | E116: ANGGOTA
A117: 114 | B117: KKAB0181 | C117: 34000478 | D117: SUGANDI | E117: ANGGOTA
A118: 115 | B118: KKAB0182 | C118: 34000552 | D118: FEBBY GUNAWAN | E118: ANGGOTA
A119: 116 | B119: KKAB0183 | C119: 34000351 | D119: ARI ROSANDI | E119: ANGGOTA
A120: 117 | B120: KKAB0184 | C120: 34000105 | D120: HERDI HERDIANA | E120: ANGGOTA
A121: 118 | B121: KKAB0186 | C121: 34000180 | D121: AGUS MUHARAM | E121: ANGGOTA
A122: 119 | B122: KKAB0187 | C122: 34000738 | D122: RAMA ANGGA K | E122: ANGGOTA
... A284: 281 | B284: KKAB0371 | C284: 34000770 | D284: CANDRA HARYANTO | E284: ANGGOTA
A285: LIST DISTRIBUSI PARCEL LEBARAN 2024 (1445H) PENGURUS
A287: No | B287: No Anggota | C287: NPP | D287: Nama Anggota | E287: STATUS | F287: SIGN
A288: 282 | B288: KKAB0001 | C288: 34000095 | D288: ARI SAEPUDIN | E288: PENGURUS KOPERASI
A289: 283 | B289: KKAB0009 | C289: 34000215 | D289: CANDRA WARSITA | E289: PENGURUS KOPERASI
A290: 284 | B290: KKAB0060 | C290: 34000112 | D290: CUCU SUHAENDI | E290: PENGURUS KOPERASI
A291: 285 | B291: KKAB0106 | C291: 34000303 | D291: JAMALUDIN ROSIHAN | E291: PENGURUS KOPERASI
A292: 286 | B292: KKAB0143 | C292: 34000221 | D292: HENDAR HAMZAH | E292: PENGURUS KOPERASI
A293: 287 | B293: KKAB0177 | C293: 34000850 | D293: DIAN ENDAH OKTAVIANA | E293: PENGURUS KOPERASI
A294: 288 | B294: KKAB0248 | C294: 34000337 | D294: YUDI WAHYUDIN | E294: PENGURUS KOPERASI
A295: 289 | B295: KKAB0303 | C295: 34000162 | D295: ERWIN SUBAGJA | E295: PENGURUS KOPERASI
A296: 290 | B296: KKAB0215 | C296: 34000264 | D296: NURDIN SAEFUROHMAN | E296: PENGURUS KOPERASI
A297: 291 | B297: KKAB0309 | C297: 34000698 | D297: AYU SHEILA MADJID | E297: PENGURUS KOPERASI
A298: 292 | D298: SYAHLA | E298: KASIR
A299: 293 | D299: SYALSA | E299: KASIR
A300: LIST DISTRIBUSI PARCEL LEBARAN 2024 (1445H) PENGURUS SPN
...
